Workbook

Sheet Summary
A1: Rooted Capital global sleeve: values screen (scored companies)
A2: As of Oct 23, 2026 · 63 companies scored in 14 country-sectors · 7 dropped by the team (see 'Dropped') · values filter only
A4: Country | B4: Sector | C4: Companies scored | D4: Pass | E4: Fail | F4: Top company | G4: Top final score | H4: Average final score
A5: Denmark | B5: Financials | C5: =COUNTIFS('All scored'!$A$2:$A$64,A5,'All scored'!$B$2:$B$64,B5) -> 4 | D5: =COUNTIFS('All scored'!$A$2:$A$64,A5,'All scored'!$B$2:$B$64,B5,'All scored'!$M$2:$M$64,"Pass") -> 2 | E5: =COUNTIFS('All scored'!$A$2:$A$64,A5,'All scored'!$B$2:$B$64,B5,'All scored'!$M$2:$M$64,"Fail") -> 2 | F5: =INDEX('All scored'!$D$2:$D$64,MATCH(1,INDEX(('All scored'!$A$2:$A$64=A5)*('All scored'!$B$2:$B$64=B5)*('All scored'!$L$2:$L$64=1),0),0)) -> Danske Bank | G5: =SUMPRODUCT(MAX(('All scored'!$A$2:$A$64=A5)*('All scored'!$B$2:$B$64=B5)*'All scored'!$K$2:$K$64)) -> 32 | H5: =AVERAGEIFS('All scored'!$K$2:$K$64,'All scored'!$A$2:$A$64,A5,'All scored'!$B$2:$B$64,B5) -> 26
A6: Denmark | B6: Health Care | C6: =COUNTIFS('All scored'!$A$2:$A$64,A6,'All scored'!$B$2:$B$64,B6) -> 6 | D6: =COUNTIFS('All scored'!$A$2:$A$64,A6,'All scored'!$B$2:$B$64,B6,'All scored'!$M$2:$M$64,"Pass") -> 3 | E6: =COUNTIFS('All scored'!$A$2:$A$64,A6,'All scored'!$B$2:$B$64,B6,'All scored'!$M$2:$M$64,"Fail") -> 3 | F6: =INDEX('All scored'!$D$2:$D$64,MATCH(1,INDEX(('All scored'!$A$2:$A$64=A6)*('All scored'!$B$2:$B$64=B6)*('All scored'!$L$2:$L$64=1),0),0)) -> Demant | G6: =SUMPRODUCT(MAX(('All scored'!$A$2:$A$64=A6)*('All scored'!$B$2:$B$64=B6)*'All scored'!$K$2:$K$64)) -> 31 | H6: =AVERAGEIFS('All scored'!$K$2:$K$64,'All scored'!$A$2:$A$64,A6,'All scored'!$B$2:$B$64,B6) -> 20.5
A7: Denmark | B7: Industrials | C7: =COUNTIFS('All scored'!$A$2:$A$64,A7,'All scored'!$B$2:$B$64,B7) -> 4 | D7: =COUNTIFS('All scored'!$A$2:$A$64,A7,'All scored'!$B$2:$B$64,B7,'All scored'!$M$2:$M$64,"Pass") -> 3 | E7: =COUNTIFS('All scored'!$A$2:$A$64,A7,'All scored'!$B$2:$B$64,B7,'All scored'!$M$2:$M$64,"Fail") -> 1 | F7: =INDEX('All scored'!$D$2:$D$64,MATCH(1,INDEX(('All scored'!$A$2:$A$64=A7)*('All scored'!$B$2:$B$64=B7)*('All scored'!$L$2:$L$64=1),0),0)) -> Vestas Wind Systems | G7: =SUMPRODUCT(MAX(('All scored'!$A$2:$A$64=A7)*('All scored'!$B$2:$B$64=B7)*'All scored'!$K$2:$K$64)) -> 26 | H7: =AVERAGEIFS('All scored'!$K$2:$K$64,'All scored'!$A$2:$A$64,A7,'All scored'!$B$2:$B$64,B7) -> 22.75
A8: Switzerland | B8: Health Care | C8: =COUNTIFS('All scored'!$A$2:$A$64,A8,'All scored'!$B$2:$B$64,B8) -> 6 | D8: =COUNTIFS('All scored'!$A$2:$A$64,A8,'All scored'!$B$2:$B$64,B8,'All scored'!$M$2:$M$64,"Pass") -> 3 | E8: =COUNTIFS('All scored'!$A$2:$A$64,A8,'All scored'!$B$2:$B$64,B8,'All scored'!$M$2:$M$64,"Fail") -> 3 | F8: =INDEX('All scored'!$D$2:$D$64,MATCH(1,INDEX(('All scored'!$A$2:$A$64=A8)*('All scored'!$B$2:$B$64=B8)*('All scored'!$L$2:$L$64=1),0),0)) -> Straumann | G8: =SUMPRODUCT(MAX(('All scored'!$A$2:$A$64=A8)*('All scored'!$B$2:$B$64=B8)*'All scored'!$K$2:$K$64)) -> 43 | H8: =AVERAGEIFS('All scored'!$K$2:$K$64,'All scored'!$A$2:$A$64,A8,'All scored'!$B$2:$B$64,B8) -> 32.833333
A9: Switzerland | B9: Industrials | C9: =COUNTIFS('All scored'!$A$2:$A$64,A9,'All scored'!$B$2:$B$64,B9) -> 4 | D9: =COUNTIFS('All scored'!$A$2:$A$64,A9,'All scored'!$B$2:$B$64,B9,'All scored'!$M$2:$M$64,"Pass") -> 2 | E9: =COUNTIFS('All scored'!$A$2:$A$64,A9,'All scored'!$B$2:$B$64,B9,'All scored'!$M$2:$M$64,"Fail") -> 2 | F9: =INDEX('All scored'!$D$2:$D$64,MATCH(1,INDEX(('All scored'!$A$2:$A$64=A9)*('All scored'!$B$2:$B$64=B9)*('All scored'!$L$2:$L$64=1),0),0)) -> Schindler Group | G9: =SUMPRODUCT(MAX(('All scored'!$A$2:$A$64=A9)*('All scored'!$B$2:$B$64=B9)*'All scored'!$K$2:$K$64)) -> 30 | H9: =AVERAGEIFS('All scored'!$K$2:$K$64,'All scored'!$A$2:$A$64,A9,'All scored'!$B$2:$B$64,B9) -> 25.5
A10: Switzerland | B10: Materials | C10: =COUNTIFS('All scored'!$A$2:$A$64,A10,'All scored'!$B$2:$B$64,B10) -> 3 | D10: =COUNTIFS('All scored'!$A$2:$A$64,A10,'All scored'!$B$2:$B$64,B10,'All scored'!$M$2:$M$64,"Pass") -> 2 | E10: =COUNTIFS('All scored'!$A$2:$A$64,A10,'All scored'!$B$2:$B$64,B10,'All scored'!$M$2:$M$64,"Fail") -> 1 | F10: =INDEX('All scored'!$D$2:$D$64,MATCH(1,INDEX(('All scored'!$A$2:$A$64=A10)*('All scored'!$B$2:$B$64=B10)*('All scored'!$L$2:$L$64=1),0),0)) -> Givaudan | G10: =SUMPRODUCT(MAX(('All scored'!$A$2:$A$64=A10)*('All scored'!$B$2:$B$64=B10)*'All scored'!$K$2:$K$64)) -> 57 | H10: =AVERAGEIFS('All scored'!$K$2:$K$64,'All scored'!$A$2:$A$64,A10,'All scored'!$B$2:$B$64,B10) -> 46.666667
A11: Taiwan | B11: Financials | C11: =COUNTIFS('All scored'!$A$2:$A$64,A11,'All scored'!$B$2:$B$64,B11) -> 6 | D11: =COUNTIFS('All scored'!$A$2:$A$64,A11,'All scored'!$B$2:$B$64,B11,'All scored'!$M$2:$M$64,"Pass") -> 3 | E11: =COUNTIFS('All scored'!$A$2:$A$64,A11,'All scored'!$B$2:$B$64,B11,'All scored'!$M$2:$M$64,"Fail") -> 3 | F11: =INDEX('All scored'!$D$2:$D$64,MATCH(1,INDEX(('All scored'!$A$2:$A$64=A11)*('All scored'!$B$2:$B$64=B11)*('All scored'!$L$2:$L$64=1),0),0)) -> Fubon Financial | G11: =SUMPRODUCT(MAX(('All scored'!$A$2:$A$64=A11)*('All scored'!$B$2:$B$64=B11)*'All scored'!$K$2:$K$64)) -> 57 | H11: =AVERAGEIFS('All scored'!$K$2:$K$64,'All scored'!$A$2:$A$64,A11,'All scored'!$B$2:$B$64,B11) -> 50.166667
A12: Taiwan | B12: Information Technology | C12: =COUNTIFS('All scored'!$A$2:$A$64,A12,'All scored'!$B$2:$B$64,B12) -> 8 | D12: =COUNTIFS('All scored'!$A$2:$A$64,A12,'All scored'!$B$2:$B$64,B12,'All scored'!$M$2:$M$64,"Pass") -> 5 | E12: =COUNTIFS('All scored'!$A$2:$A$64,A12,'All scored'!$B$2:$B$64,B12,'All scored'!$M$2:$M$64,"Fail") -> 3 | F12: =INDEX('All scored'!$D$2:$D$64,MATCH(1,INDEX(('All scored'!$A$2:$A$64=A12)*('All scored'!$B$2:$B$64=B12)*('All scored'!$L$2:$L$64=1),0),0)) -> ASUS | G12: =SUMPRODUCT(MAX(('All scored'!$A$2:$A$64=A12)*('All scored'!$B$2:$B$64=B12)*'All scored'!$K$2:$K$64)) -> 54 | H12: =AVERAGEIFS('All scored'!$K$2:$K$64,'All scored'!$A$2:$A$64,A12,'All scored'!$B$2:$B$64,B12) -> 37.75
A13: Indonesia | B13: Communication Services | C13: =COUNTIFS('All scored'!$A$2:$A$64,A13,'All scored'!$B$2:$B$64,B13) -> 3 | D13: =COUNTIFS('All scored'!$A$2:$A$64,A13,'All scored'!$B$2:$B$64,B13,'All scored'!$M$2:$M$64,"Pass") -> 2 | E13: =COUNTIFS('All scored'!$A$2:$A$64,A13,'All scored'!$B$2:$B$64,B13,'All scored'!$M$2:$M$64,"Fail") -> 1 | F13: =INDEX('All scored'!$D$2:$D$64,MATCH(1,INDEX(('All scored'!$A$2:$A$64=A13)*('All scored'!$B$2:$B$64=B13)*('All scored'!$L$2:$L$64=1),0),0)) -> Elang Mahkota Teknologi | G13: =SUMPRODUCT(MAX(('All scored'!$A$2:$A$64=A13)*('All scored'!$B$2:$B$64=B13)*'All scored'!$K$2:$K$64)) -> 57 | H13: =AVERAGEIFS('All scored'!$K$2:$K$64,'All scored'!$A$2:$A$64,A13,'All scored'!$B$2:$B$64,B13) -> 44
A14: Indonesia | B14: Consumer Staples | C14: =COUNTIFS('All scored'!$A$2:$A$64,A14,'All scored'!$B$2:$B$64,B14) -> 4 | D14: =COUNTIFS('All scored'!$A$2:$A$64,A14,'All scored'!$B$2:$B$64,B14,'All scored'!$M$2:$M$64,"Pass") -> 2 | E14: =COUNTIFS('All scored'!$A$2:$A$64,A14,'All scored'!$B$2:$B$64,B14,'All scored'!$M$2:$M$64,"Fail") -> 2 | F14: =INDEX('All scored'!$D$2:$D$64,MATCH(1,INDEX(('All scored'!$A$2:$A$64=A14)*('All scored'!$B$2:$B$64=B14)*('All scored'!$L$2:$L$64=1),0),0)) -> Astra Agro Lestari | G14: =SUMPRODUCT(MAX(('All scored'!$A$2:$A$64=A14)*('All scored'!$B$2:$B$64=B14)*'All scored'!$K$2:$K$64)) -> 35 | H14: =AVERAGEIFS('All scored'!$K$2:$K$64,'All scored'!$A$2:$A$64,A14,'All scored'!$B$2:$B$64,B14) -> 31.5
A15: Indonesia | B15: Financials | C15: =COUNTIFS('All scored'!$A$2:$A$64,A15,'All scored'!$B$2:$B$64,B15) -> 2 | D15: =COUNTIFS('All scored'!$A$2:$A$64,A15,'All scored'!$B$2:$B$64,B15,'All scored'!$M$2:$M$64,"Pass") -> 1 | E15: =COUNTIFS('All scored'!$A$2:$A$64,A15,'All scored'!$B$2:$B$64,B15,'All scored'!$M$2:$M$64,"Fail") -> 1 | F15: =INDEX('All scored'!$D$2:$D$64,MATCH(1,INDEX(('All scored'!$A$2:$A$64=A15)*('All scored'!$B$2:$B$64=B15)*('All scored'!$L$2:$L$64=1),0),0)) -> Bank Mandiri | G15: =SUMPRODUCT(MAX(('All scored'!$A$2:$A$64=A15)*('All scored'!$B$2:$B$64=B15)*'All scored'!$K$2:$K$64)) -> 56 | H15: =AVERAGEIFS('All scored'!$K$2:$K$64,'All scored'!$A$2:$A$64,A15,'All scored'!$B$2:$B$64,B15) -> 54.5
A16: Singapore | B16: Financials | C16: =COUNTIFS('All scored'!$A$2:$A$64,A16,'All scored'!$B$2:$B$64,B16) -> 5 | D16: =COUNTIFS('All scored'!$A$2:$A$64,A16,'All scored'!$B$2:$B$64,B16,'All scored'!$M$2:$M$64,"Pass") -> 3 | E16: =COUNTIFS('All scored'!$A$2:$A$64,A16,'All scored'!$B$2:$B$64,B16,'All scored'!$M$2:$M$64,"Fail") -> 2 | F16: =INDEX('All scored'!$D$2:$D$64,MATCH(1,INDEX(('All scored'!$A$2:$A$64=A16)*('All scored'!$B$2:$B$64=B16)*('All scored'!$L$2:$L$64=1),0),0)) -> UOB | G16: =SUMPRODUCT(MAX(('All scored'!$A$2:$A$64=A16)*('All scored'!$B$2:$B$64=B16)*'All scored'!$K$2:$K$64)) -> 53 | H16: =AVERAGEIFS('All scored'!$K$2:$K$64,'All scored'!$A$2:$A$64,A16,'All scored'!$B$2:$B$64,B16) -> 43.6
... A18: Singapore | B18: Real Estate | C18: =COUNTIFS('All scored'!$A$2:$A$64,A18,'All scored'!$B$2:$B$64,B18) -> 4 | D18: =COUNTIFS('All scored'!$A$2:$A$64,A18,'All scored'!$B$2:$B$64,B18,'All scored'!$M$2:$M$64,"Pass") -> 2 | E18: =COUNTIFS('All scored'!$A$2:$A$64,A18,'All scored'!$B$2:$B$64,B18,'All scored'!$M$2:$M$64,"Fail") -> 2 | F18: =INDEX('All scored'!$D$2:$D$64,MATCH(1,INDEX(('All scored'!$A$2:$A$64=A18)*('All scored'!$B$2:$B$64=B18)*('All scored'!$L$2:$L$64=1),0),0)) -> CapitaLand Integrated Commercial Trust | G18: =SUMPRODUCT(MAX(('All scored'!$A$2:$A$64=A18)*('All scored'!$B$2:$B$64=B18)*'All scored'!$K$2:$K$64)) -> 34 | H18: =AVERAGEIFS('All scored'!$K$2:$K$64,'All scored'!$A$2:$A$64,A18,'All scored'!$B$2:$B$64,B18) -> 21.5
A19: Total | C19: =SUM(C5:C18) -> 63 | D19: =SUM(D5:D18) -> 35 | E19: =SUM(E5:E18) -> 28 | H19: =AVERAGE('All scored'!$K$2:$K$64) -> 34.142857
A21: Pass = top half of the country-sector by final score, ties included. Ties for the top spot show the first company listed; see 'All scored' for full ranks.
A22: Sources: fiscal-2025 annual reports from official exchange filing sites (Nasdaq Copenhagen, MOPS, SGX) or company websites; 20-Fs from SEC EDGAR for Genmab, Alcon and Telkom.

Sheet Pass list
A1: Country | B1: Sector | C1: Rank | D1: Ticker | E1: Company | F1: Final score | G1: Strongest theme
A2: Denmark | B2: Financials | C2: 1 | D2: DANSKE.CO | E2: Danske Bank | F2: 32 | G2: Community 3 from Leadership development programme for employees, expanded in 2025 and m
A3: Denmark | B3: Financials | C3: 2 | D3: ALSYDB.CO | E3: AL Sydbank A/S | F3: 30 | G3: Cross-cultural 2 from Dedicated Sunflower phone line where trained staff assist customers wi
A4: Denmark | B4: Health Care | C4: 1 | D4: DEMANT.CO | E4: Demant | F4: 31 | G4: Cross-cultural 4 from Core business sells hearing aids (assistive technology) and runs clini
A5: Denmark | B5: Health Care | C5: 2 | D5: HLUN-B.CO | E5: Lundbeck | F5: 29 | G5: Community 3 from Enterprise Leadership Program rolled out to train and develop the comp
A6: Denmark | B6: Health Care | C6: 3 | D6: BAVA.CO | E6: Bavarian Nordic | F6: 27 | G6: Cross-cultural 3 from Lowest-price mpox vaccine access for low- and lower-middle-income coun
A7: Denmark | B7: Industrials | C7: 1 | D7: VWS.CO | E7: Vestas Wind Systems | F7: 26 | G7: Entrepreneurship 2 from Technical training, capacity building and entrepreneurship courses for
A8: Denmark | B8: Industrials | C8: 2 | D8: DNORD.CO | E8: D/S Norden | F8: 23 | G8: Cross-cultural 2 from Bias-mitigating recruitment practices, including diverse panels and a
A9: Denmark | B9: Industrials | C9: 2 | D9: MAERSK-B.CO | E9: Maersk | F9: 23 | G9: Cross-cultural 2 from Whistleblower mechanism available in many languages for employees and
A10: Switzerland | B10: Health Care | C10: 1 | D10: STMN.SW | E10: Straumann | F10: 43 | G10: Community 3 from Global clinical education programme for dental professionals, run with
A11: Switzerland | B11: Health Care | C11: 2 | D11: SOON.SW | E11: Sonova | F11: 40 | G11: Cross-cultural 3 from Global employee resource groups, including OutLoud and Hearing Loss ne
A12: Switzerland | B12: Health Care | C12: 3 | D12: GALD.SW | E12: Galderma Group | F12: 36 | G12: Community 3 from Galderma Aesthetic Injector Network (GAIN), a global hands-on clinical
A13: Switzerland | B13: Industrials | C13: 1 | D13: SCHN.SW | E13: Schindler Group | F13: 30 | G13: Cross-cultural 2 from Accessibility features (induction loops, voice signaling, Braille) ins
... A36: Singapore | B36: Real Estate | C36: 2 | D36: K71U.SI | E36: Keppel REIT | F36: 20 | G36: Cross-cultural 2 from Training on unconscious bias and inclusive leadership for employees
A38: Snapshot of the 'Values result' column on Oct 23, 2026 (sorted by country, sector, rank).

Sheet All scored
A1: Country | B1: Sector | C1: Ticker | D1: Company | E1: Creativity (0-5) | F1: Community (0-5) | G1: Cross-cultural (0-5) | H1: Entrepreneurship (0-5) | I1: Alignment score (0-100) | J1: Red flag deduction | K1: Final score | L1: Country-sector rank | M1: Values result | N1: Red flags | O1: Third component (TBD) | P1: Thin-coverage themes | Q1: Score source | R1: Document | S1: Fiscal year | T1: Source site | U1: Report link | V1: Language | W1: Words read | X1: Notes | Y1: Flags for review
A2: Denmark | B2: Financials | C2: DANSKE.CO | D2: Danske Bank | E2: 0 | F2: 3 | G2: 2 | H2: 2 | I2: =E2/5*35+F2/5*30+G2/5*20+H2/5*15 -> 32 | J2: 0 | K2: =MAX(0,I2-J2) -> 32 | L2: =COUNTIFS($A$2:$A$64,A2,$B$2:$B$64,B2,$K$2:$K$64,">"&K2)+1 -> 1 | M2: =IF(L2<=CEILING(COUNTIFS($A$2:$A$64,A2,$B$2:$B$64,B2)/2,1),"Pass","Fail") -> Pass | Q2: Annual report 2025 | R2: Annual report | S2: 2025 | T2: company website | U2: https://danskebank.com/-/media/danske-bank-com/file-cloud/2026/2/annual-report-2025.pdf?rev=16af459cfa094b8ab365a911a324f7f2 | V2: English | W2: 39956 | X2: Top half of Denmark Financials; Community 3 from Leadership development programme for employees, expanded in 2025 and m; red flag: none; Discloses internally substantiated discrimination/harassment cases; not a red flag under the rule.
A3: Denmark | B3: Financials | C3: ALSYDB.CO | D3: AL Sydbank A/S | E3: 1 | F3: 2 | G3: 2 | H3: 1 | I3: =E3/5*35+F3/5*30+G3/5*20+H3/5*15 -> 30 | J3: 0 | K3: =MAX(0,I3-J3) -> 30 | L3: =COUNTIFS($A$2:$A$64,A3,$B$2:$B$64,B3,$K$2:$K$64,">"&K3)+1 -> 2 | M3: =IF(L3<=CEILING(COUNTIFS($A$2:$A$64,A3,$B$2:$B$64,B3)/2,1),"Pass","Fail") -> Pass | Q3: Annual report 2025 | R3: Annual report | S3: 2025 | T3: Nasdaq Copenhagen company announcements | U3: https://attachment.news.eu.nasdaq.com/a636006377807c5474acd3b1ab00500e5 | V3: English | W3: 15216 | X3: Top half of Denmark Financials; Cross-cultural 2 from Dedicated Sunflower phone line where trained staff assist customers wi; red flag: none
A4: Denmark | B4: Financials | C4: JYSK.CO | D4: Jyske Bank | E4: 0 | F4: 2 | G4: 2 | H4: 1 | I4: =E4/5*35+F4/5*30+G4/5*20+H4/5*15 -> 23 | J4: 0 | K4: =MAX(0,I4-J4) -> 23 | L4: =COUNTIFS($A$2:$A$64,A4,$B$2:$B$64,B4,$K$2:$K$64,">"&K4)+1 -> 3 | M4: =IF(L4<=CEILING(COUNTIFS($A$2:$A$64,A4,$B$2:$B$64,B4)/2,1),"Pass","Fail") -> Fail | Q4: Annual report 2025 | R4: Annual report | S4: 2025 | T4: Nasdaq Copenhagen company announcements | U4: https://attachment.news.eu.nasdaq.com/a11687649947912d72fafbdc8f0845e19 | V4: English | W4: 17877 | X4: Not in top half of Denmark Financials; Cross-cultural 2 from Participation in the Sunflower programme to support customers with inv; red flag: none | Y4: TOC fallback (no usable table of contents): keyword paragraphs across the whole report; skipped 32 of 264 pages (risk, number pages, financial statements from page 257, except 8 governance/sustainability page(s) after them)
A5: Denmark | B5: Financials | C5: DJUR.CO | D5: Djurslands Bank A/S | E5: 0 | F5: 2 | G5: 1 | H5: 1 | I5: =E5/5*35+F5/5*30+G5/5*20+H5/5*15 -> 19 | J5: 0 | K5: =MAX(0,I5-J5) -> 19 | L5: =COUNTIFS($A$2:$A$64,A5,$B$2:$B$64,B5,$K$2:$K$64,">"&K5)+1 -> 4 | M5: =IF(L5<=CEILING(COUNTIFS($A$2:$A$64,A5,$B$2:$B$64,B5)/2,1),"Pass","Fail") -> Fail | P5: community, cross-cultural | Q5: Annual report 2025 | R5: Annual report | S5: 2025 | T5: Nasdaq Copenhagen company announcements | U5: https://attachment.news.eu.nasdaq.com/a610db5d4df88710ac547817939aacd8f | V5: Non-English | W5: 10204 | X5: Not in top half of Denmark Financials; Community 2 from Structured professional and personal skills development for all employ; red flag: none; non-English source | Y5: coverage insufficient (community, cross_cultural); second look: no standalone report found
A6: Denmark | B6: Health Care | C6: DEMANT.CO | D6: Demant | E6: 0 | F6: 2 | G6: 4 | H6: 1 | I6: =E6/5*35+F6/5*30+G6/5*20+H6/5*15 -> 31 | J6: 0 | K6: =MAX(0,I6-J6) -> 31 | L6: =COUNTIFS($A$2:$A$64,A6,$B$2:$B$64,B6,$K$2:$K$64,">"&K6)+1 -> 1 | M6: =IF(L6<=CEILING(COUNTIFS($A$2:$A$64,A6,$B$2:$B$64,B6)/2,1),"Pass","Fail") -> Pass | Q6: Annual report 2025 | R6: Annual report | S6: 2025 | T6: company website | U6: https://assets-we.cas.dgs.com/-/media/demant/shared/new-library-2022/financial-reports/annual-report-english/demant-annual-report-2025.pdf?la=en&rev=AE32&hash=F68551D4B2CB09858AD389A748D55FF6 | V6: English | W6: 34662 | X6: Top half of Denmark Health Care; Cross-cultural 4 from Core business sells hearing aids (assistive technology) and runs clini; red flag: none; Discloses internally substantiated discrimination and/or harassment cases; not a red flag under the rule.
A7: Denmark | B7: Health Care | C7: HLUN-B.CO | D7: Lundbeck | E7: 0 | F7: 3 | G7: 2 | H7: 1 | I7: =E7/5*35+F7/5*30+G7/5*20+H7/5*15 -> 29 | J7: 0 | K7: =MAX(0,I7-J7) -> 29 | L7: =COUNTIFS($A$2:$A$64,A7,$B$2:$B$64,B7,$K$2:$K$64,">"&K7)+1 -> 2 | M7: =IF(L7<=CEILING(COUNTIFS($A$2:$A$64,A7,$B$2:$B$64,B7)/2,1),"Pass","Fail") -> Pass | Q7: Annual report 2025 | R7: Annual report | S7: 2025 | T7: company website | U7: https://www.lundbeck.com/content/dam/lundbeck-com/masters/global-site/annual-reporting/2025/Lundbeck_Annual_Report_2025.pdf | V7: English | W7: 40149 | X7: Top half of Denmark Health Care; Community 3 from Enterprise Leadership Program rolled out to train and develop the comp; red flag: none; Discloses internally substantiated harassment and/or discrimination cases; not a red flag under the rule. | Y7: E5: figure(s) not found near the quote, removed: 93 community: needs human review: figure(s) removed from cited evidence E5; the level may be lower
A8: Denmark | B8: Health Care | C8: BAVA.CO | D8: Bavarian Nordic | E8: 0 | F8: 2 | G8: 3 | H8: 1 | I8: =E8/5*35+F8/5*30+G8/5*20+H8/5*15 -> 27 | J8: 0 | K8: =MAX(0,I8-J8) -> 27 | L8: =COUNTIFS($A$2:$A$64,A8,$B$2:$B$64,B8,$K$2:$K$64,">"&K8)+1 -> 3 | M8: =IF(L8<=CEILING(COUNTIFS($A$2:$A$64,A8,$B$2:$B$64,B8)/2,1),"Pass","Fail") -> Pass | Q8: Annual report 2025 | R8: Annual report | S8: 2025 | T8: company website | U8: https://www.bavarian-nordic.com/media/380028/bn_annual_report_2025.pdf | V8: English | W8: 39980 | X8: Top half of Denmark Health Care; Cross-cultural 3 from Lowest-price mpox vaccine access for low- and lower-middle-income coun; red flag: none; Discloses internally substantiated discrimination, including harassment cases; not a red flag under the rule.
A9: Denmark | B9: Health Care | C9: ZEAL.CO | D9: Zealand Pharma | E9: 0 | F9: 2 | G9: 2 | H9: 1 | I9: =E9/5*35+F9/5*30+G9/5*20+H9/5*15 -> 23 | J9: 0 | K9: =MAX(0,I9-J9) -> 23 | L9: =COUNTIFS($A$2:$A$64,A9,$B$2:$B$64,B9,$K$2:$K$64,">"&K9)+1 -> 4 | M9: =IF(L9<=CEILING(COUNTIFS($A$2:$A$64,A9,$B$2:$B$64,B9)/2,1),"Pass","Fail") -> Fail | Q9: Annual report 2025 | R9: Annual report | S9: 2025 | T9: company website | U9: https://www.zealandpharma.com/media/2oeew4jl/zealand-pharma-annual-report-2025.pdf | V9: English | W9: 24438 | X9: Not in top half of Denmark Health Care; Cross-cultural 2 from Inclusiveness Index built into the employee engagement survey to give ; red flag: none
A10: Denmark | B10: Health Care | C10: CHEMM.CO | D10: ChemoMetec | E10: 0 | F10: 1 | G10: 1 | H10: 1 | I10: =E10/5*35+F10/5*30+G10/5*20+H10/5*15 -> 13 | J10: 0 | K10: =MAX(0,I10-J10) -> 13 | L10: =COUNTIFS($A$2:$A$64,A10,$B$2:$B$64,B10,$K$2:$K$64,">"&K10)+1 -> 5 | M10: =IF(L10<=CEILING(COUNTIFS($A$2:$A$64,A10,$B$2:$B$64,B10)/2,1),"Pass","Fail") -> Fail | Q10: Annual report 2025 | R10: Annual report | S10: 2025 | T10: Nasdaq Copenhagen company announcements | U10: https://attachment.news.eu.nasdaq.com/a772ca2d52624dd57c81a282b8e1fb8aa | V10: English | W10: 21495 | X10: Not in top half of Denmark Health Care; no theme above 1; red flag: none
A11: Denmark | B11: Health Care | C11: GMAB | D11: Genmab | E11: 0 | F11: 0 | G11: 0 | H11: 0 | I11: =E11/5*35+F11/5*30+G11/5*20+H11/5*15 -> 0 | J11: 0 | K11: =MAX(0,I11-J11) -> 0 | L11: =COUNTIFS($A$2:$A$64,A11,$B$2:$B$64,B11,$K$2:$K$64,">"&K11)+1 -> 6 | M11: =IF(L11<=CEILING(COUNTIFS($A$2:$A$64,A11,$B$2:$B$64,B11)/2,1),"Pass","Fail") -> Fail | P11: community, cross-cultural | Q11: 20-F 2025 | R11: 20-F | S11: 2025 | T11: SEC EDGAR | U11: https://www.sec.gov/Archives/edgar/data/1434265/000143426526000014/gmab-20251231_d2.htm | V11: English | W11: 24493 | X11: Not in top half of Denmark Health Care; no theme above 1; red flag: none | Y11: coverage insufficient (community, cross_cultural); second look: no standalone report found
A12: Denmark | B12: Industrials | C12: VWS.CO | D12: Vestas Wind Systems | E12: 0 | F12: 2 | G12: 2 | H12: 2 | I12: =E12/5*35+F12/5*30+G12/5*20+H12/5*15 -> 26 | J12: 0 | K12: =MAX(0,I12-J12) -> 26 | L12: =COUNTIFS($A$2:$A$64,A12,$B$2:$B$64,B12,$K$2:$K$64,">"&K12)+1 -> 1 | M12: =IF(L12<=CEILING(COUNTIFS($A$2:$A$64,A12,$B$2:$B$64,B12)/2,1),"Pass","Fail") -> Pass | Q12: Annual report 2025 | R12: Annual report | S12: 2025 | T12: company website | U12: https://www.vestas.com/content/dam/vestas-com/global/en/investor/reports-and-presentations/financial/2025/fy-2025/Vestas%20Annual%20Report%202025.pdf.coredownload.inline.pdf | V12: English | W12: 40183 | X12: Top half of Denmark Industrials; Entrepreneurship 2 from Technical training, capacity building and entrepreneurship courses for; red flag: none; Discloses internally substantiated discrimination/harassment/labour rights (ethicsline social and human rights complaints) cases; not a red flag under the rule.
A13: Denmark | B13: Industrials | C13: DNORD.CO | D13: D/S Norden | E13: 0 | F13: 2 | G13: 2 | H13: 1 | I13: =E13/5*35+F13/5*30+G13/5*20+H13/5*15 -> 23 | J13: 0 | K13: =MAX(0,I13-J13) -> 23 | L13: =COUNTIFS($A$2:$A$64,A13,$B$2:$B$64,B13,$K$2:$K$64,">"&K13)+1 -> 2 | M13: =IF(L13<=CEILING(COUNTIFS($A$2:$A$64,A13,$B$2:$B$64,B13)/2,1),"Pass","Fail") -> Pass | Q13: Annual report 2025 | R13: Annual report | S13: 2025 | T13: Nasdaq Copenhagen company announcements | U13: https://attachment.news.eu.nasdaq.com/ac6824c31a47a615477d702aedbbdb9ad#esef | V13: English | W13: 19517 | X13: Top half of Denmark Industrials; Cross-cultural 2 from Bias-mitigating recruitment practices, including diverse panels and a ; red flag: none
A14: Denmark | B14: Industrials | C14: MAERSK-B.CO | D14: Maersk | E14: 0 | F14: 2 | G14: 2 | H14: 1 | I14: =E14/5*35+F14/5*30+G14/5*20+H14/5*15 -> 23 | J14: 0 | K14: =MAX(0,I14-J14) -> 23 | L14: =COUNTIFS($A$2:$A$64,A14,$B$2:$B$64,B14,$K$2:$K$64,">"&K14)+1 -> 2 | M14: =IF(L14<=CEILING(COUNTIFS($A$2:$A$64,A14,$B$2:$B$64,B14)/2,1),"Pass","Fail") -> Pass | Q14: Annual report 2025 | R14: Annual report | S14: 2025 | T14: Nasdaq Copenhagen company announcements | U14: https://attachment.news.eu.nasdaq.com/aa5bc3ccc5e259aa01dbe8bff4f0995b1 | V14: English | W14: 20969 | X14: Top half of Denmark Industrials; Cross-cultural 2 from Whistleblower mechanism available in many languages for employees and ; red flag: none; Discloses internally substantiated discrimination cases; not a red flag under the rule.
A15: Denmark | B15: Industrials | C15: NTG.CO | D15: NTG Nordic Transport Group A/S | E15: 0 | F15: 2 | G15: 1 | H15: 1 | I15: =E15/5*35+F15/5*30+G15/5*20+H15/5*15 -> 19 | J15: 0 | K15: =MAX(0,I15-J15) -> 19 | L15: =COUNTIFS($A$2:$A$64,A15,$B$2:$B$64,B15,$K$2:$K$64,">"&K15)+1 -> 4 | M15: =IF(L15<=CEILING(COUNTIFS($A$2:$A$64,A15,$B$2:$B$64,B15)/2,1),"Pass","Fail") -> Fail | Q15: Annual report 2025 | R15: Annual report | S15: 2025 | T15: Nasdaq Copenhagen company announcements | U15: https://attachment.news.eu.nasdaq.com/a35279cd1e1c3779db793f83af61e92e8 | V15: English | W15: 18578 | X15: Not in top half of Denmark Industrials; Community 2 from New central People & Culture function to develop employees across the ; red flag: none
A16: Switzerland | B16: Health Care | C16: STMN.SW | D16: Straumann | E16: 2 | F16: 3 | G16: 2 | H16: 1 | I16: =E16/5*35+F16/5*30+G16/5*20+H16/5*15 -> 43 | J16: 0 | K16: =MAX(0,I16-J16) -> 43 | L16: =COUNTIFS($A$2:$A$64,A16,$B$2:$B$64,B16,$K$2:$K$64,">"&K16)+1 -> 1 | M16: =IF(L16<=CEILING(COUNTIFS($A$2:$A$64,A16,$B$2:$B$64,B16)/2,1),"Pass","Fail") -> Pass | Q16: Annual report 2025 | R16: Annual report | S16: 2025 | T16: company website | U16: https://www.straumann.com/content/dam/media-center/group/en/documents/annual-report/2025/Straumann_AR25.pdf | V16: English | W16: 40146 | X16: Top half of Switzerland Health Care; Community 3 from Global clinical education programme for dental professionals, run with; red flag: none; Discloses internally substantiated discrimination and harassment cases; not a red flag under the rule.
A17: Switzerland | B17: Health Care | C17: SOON.SW | D17: Sonova | E17: 1 | F17: 3 | G17: 3 | H17: 1 | I17: =E17/5*35+F17/5*30+G17/5*20+H17/5*15 -> 40 | J17: 0 | K17: =MAX(0,I17-J17) -> 40 | L17: =COUNTIFS($A$2:$A$64,A17,$B$2:$B$64,B17,$K$2:$K$64,">"&K17)+1 -> 2 | M17: =IF(L17<=CEILING(COUNTIFS($A$2:$A$64,A17,$B$2:$B$64,B17)/2,1),"Pass","Fail") -> Pass | Q17: Annual report 2025 | R17: Annual report | S17: 2025 | T17: company website | U17: https://www.sonova.com/wp-content/uploads/2026/05/01_Sonova_AR_25-26_Full_Report_en.pdf | V17: English | W17: 38892 | X17: Top half of Switzerland Health Care; Cross-cultural 3 from Global employee resource groups, including OutLoud and Hearing Loss ne; red flag: none
A18: Switzerland | B18: Health Care | C18: GALD.SW | D18: Galderma Group | E18: 1 | F18: 3 | G18: 2 | H18: 1 | I18: =E18/5*35+F18/5*30+G18/5*20+H18/5*15 -> 36 | J18: 0 | K18: =MAX(0,I18-J18) -> 36 | L18: =COUNTIFS($A$2:$A$64,A18,$B$2:$B$64,B18,$K$2:$K$64,">"&K18)+1 -> 3 | M18: =IF(L18<=CEILING(COUNTIFS($A$2:$A$64,A18,$B$2:$B$64,B18)/2,1),"Pass","Fail") -> Pass | Q18: Annual report 2025 | R18: Annual report | S18: 2025 | T18: company website | U18: https://www.galderma.com/sites/default/files/2026-03/galderma_ar_2025_consolidated-doc_8b_260304_-_full.pdf | V18: English | W18: 23690 | X18: Top half of Switzerland Health Care; Community 3 from Galderma Aesthetic Injector Network (GAIN), a global hands-on clinical; red flag: none
A19: Switzerland | B19: Health Care | C19: SDZ.SW | D19: Sandoz Group | E19: 0 | F19: 3 | G19: 3 | H19: 1 | I19: =E19/5*35+F19/5*30+G19/5*20+H19/5*15 -> 33 | J19: 0 | K19: =MAX(0,I19-J19) -> 33 | L19: =COUNTIFS($A$2:$A$64,A19,$B$2:$B$64,B19,$K$2:$K$64,">"&K19)+1 -> 4 | M19: =IF(L19<=CEILING(COUNTIFS($A$2:$A$64,A19,$B$2:$B$64,B19)/2,1),"Pass","Fail") -> Fail | Q19: Annual report 2025 | R19: Annual report | S19: 2025 | T19: company website | U19: https://sandoz-com.cms.sandoz.com/sites/default/files/Media%20Documents/Sandoz%20Integrated%20Annual%20Report%202025.pdf | V19: English | W19: 24128 | X19: Not in top half of Switzerland Health Care; Cross-cultural 3 from Access program for low- and middle-income countries: lower prices, lic; red flag: none; Discloses internally substantiated harassment cases; not a red flag under the rule.
A20: Switzerland | B20: Health Care | C20: LONN.SW | D20: Lonza | E20: 0 | F20: 2 | G20: 2 | H20: 1 | I20: =E20/5*35+F20/5*30+G20/5*20+H20/5*15 -> 23 | J20: 0 | K20: =MAX(0,I20-J20) -> 23 | L20: =COUNTIFS($A$2:$A$64,A20,$B$2:$B$64,B20,$K$2:$K$64,">"&K20)+1 -> 5 | M20: =IF(L20<=CEILING(COUNTIFS($A$2:$A$64,A20,$B$2:$B$64,B20)/2,1),"Pass","Fail") -> Fail | Q20: Annual report 2025 | R20: Annual report | S20: 2025 | T20: SGX company announcements (secondary listing | U20: ) https://links.sgx.com/1.0.0/corporate-announcements/LJE7WPRJD5EBVAED/881490_Lonza%20Annual%20Report%202025.pdf | V20: English | W20: 18235 | X20: Not in top half of Switzerland Health Care; Cross-cultural 2 from HR practice allowing employees to self-identify as transgender or not ; red flag: none
A21: Switzerland | B21: Health Care | C21: ALC | D21: Alcon | E21: 0 | F21: 2 | G21: 1 | H21: 2 | I21: =E21/5*35+F21/5*30+G21/5*20+H21/5*15 -> 22 | J21: 0 | K21: =MAX(0,I21-J21) -> 22 | L21: =COUNTIFS($A$2:$A$64,A21,$B$2:$B$64,B21,$K$2:$K$64,">"&K21)+1 -> 6 | M21: =IF(L21<=CEILING(COUNTIFS($A$2:$A$64,A21,$B$2:$B$64,B21)/2,1),"Pass","Fail") -> Fail | P21: cross-cultural | Q21: 20-F 2025 | R21: 20-F | S21: 2025 | T21: SEC EDGAR | U21: https://www.sec.gov/Archives/edgar/data/1167379/000116737926000014/alc-20251231.htm | V21: English | W21: 16328 | X21: Not in top half of Switzerland Health Care; Entrepreneurship 2 from Alcon Seed Fund supports the Eye Pitch Live pitch competition where en; red flag: none | Y21: coverage insufficient (cross_cultural); second look: no standalone report found
A22: Switzerland | B22: Industrials | C22: SCHN.SW | D22: Schindler Group | E22: 1 | F22: 2 | G22: 2 | H22: 1 | I22: =E22/5*35+F22/5*30+G22/5*20+H22/5*15 -> 30 | J22: 0 | K22: =MAX(0,I22-J22) -> 30 | L22: =COUNTIFS($A$2:$A$64,A22,$B$2:$B$64,B22,$K$2:$K$64,">"&K22)+1 -> 1 | M22: =IF(L22<=CEILING(COUNTIFS($A$2:$A$64,A22,$B$2:$B$64,B22)/2,1),"Pass","Fail") -> Pass | Q22: Annual report 2025 | R22: Annual report | S22: 2025 | T22: company website | U22: https://group.schindler.com/content/dam/website/group/docs/investors/2025/2025-schindler-fy-group-review-en.pdf/_jcr_content/renditions/original./2025-schindler-fy-group-review-en.pdf | V22: English | W22: 8316 | X22: Top half of Switzerland Industrials; Cross-cultural 2 from Accessibility features (induction loops, voice signaling, Braille) ins; red flag: none
A23: Switzerland | B23: Industrials | C23: ACLN.SW | D23: Accelleron Industries | E23: 0 | F23: 3 | G23: 2 | H23: 1 | I23: =E23/5*35+F23/5*30+G23/5*20+H23/5*15 -> 29 | J23: 0 | K23: =MAX(0,I23-J23) -> 29 | L23: =COUNTIFS($A$2:$A$64,A23,$B$2:$B$64,B23,$K$2:$K$64,">"&K23)+1 -> 2 | M23: =IF(L23<=CEILING(COUNTIFS($A$2:$A$64,A23,$B$2:$B$64,B23)/2,1),"Pass","Fail") -> Pass | Q23: Annual report 2025 | R23: Annual report | S23: 2025 | T23: company website | U23: https://accelleron.com/content/dam/accelleronind/documents/investors/accelleron-annual-report-2025.pdf | V23: English | W23: 39253 | X23: Top half of Switzerland Industrials; Community 3 from Group-wide employee-led community engagement program of volunteering a; red flag: none
A24: Switzerland | B24: Industrials | C24: BEAN.SW | D24: BELIMO Holding | E24: 0 | F24: 2 | G24: 3 | H24: 0 | I24: =E24/5*35+F24/5*30+G24/5*20+H24/5*15 -> 24 | J24: 0 | K24: =MAX(0,I24-J24) -> 24 | L24: =COUNTIFS($A$2:$A$64,A24,$B$2:$B$64,B24,$K$2:$K$64,">"&K24)+1 -> 3 | M24: =IF(L24<=CEILING(COUNTIFS($A$2:$A$64,A24,$B$2:$B$64,B24)/2,1),"Pass","Fail") -> Fail | Q24: Annual report 2025 | R24: Annual report | S24: 2025 | T24: company website | U24: https://report.belimo.com/ar25/app/uploads/Annual-Report-2025.pdf | V24: English | W24: 30231 | X24: Not in top half of Switzerland Industrials; Cross-cultural 3 from Participation in disability employment programs that bring people with; red flag: none
A25: Switzerland | B25: Industrials | C25: GEBN.SW | D25: Geberit | E25: 0 | F25: 2 | G25: 1 | H25: 1 | I25: =E25/5*35+F25/5*30+G25/5*20+H25/5*15 -> 19 | J25: 0 | K25: =MAX(0,I25-J25) -> 19 | L25: =COUNTIFS($A$2:$A$64,A25,$B$2:$B$64,B25,$K$2:$K$64,">"&K25)+1 -> 4 | M25: =IF(L25<=CEILING(COUNTIFS($A$2:$A$64,A25,$B$2:$B$64,B25)/2,1),"Pass","Fail") -> Fail | Q25: Annual report 2025 | R25: Annual report | S25: 2025 | T25: company website | U25: https://reports.geberit.com/annual-report/2025/_assets/downloads/geberit-ar25-en-entire.pdf | V25: English | W25: 39904 | X25: Not in top half of Switzerland Industrials; Community 2 from Internal GROW and LEAD talent and leadership development programmes fo; red flag: none; Discloses internally substantiated sexual harassment cases; not a red flag under the rule.
A26: Switzerland | B26: Materials | C26: GIVN.SW | D26: Givaudan | E26: 3 | F26: 3 | G26: 3 | H26: 2 | I26: =E26/5*35+F26/5*30+G26/5*20+H26/5*15 -> 57 | J26: 0 | K26: =MAX(0,I26-J26) -> 57 | L26: =COUNTIFS($A$2:$A$64,A26,$B$2:$B$64,B26,$K$2:$K$64,">"&K26)+1 -> 1 | M26: =IF(L26<=CEILING(COUNTIFS($A$2:$A$64,A26,$B$2:$B$64,B26)/2,1),"Pass","Fail") -> Pass | Q26: Annual report 2025 | R26: Annual report | S26: 2025 | T26: company website | U26: https://www.givaudan.com/file/1366761/download | V26: English | W26: 40036 | X26: Top half of Switzerland Materials; Cross-cultural 3 from Employee Community Groups for women, ethnic groups and LGBTQIA+ employ; red flag: none
A27: Switzerland | B27: Materials | C27: DSFIR.AS | D27: DSM-Firmenich | E27: 3 | F27: 3 | G27: 2 | H27: 2 | I27: =E27/5*35+F27/5*30+G27/5*20+H27/5*15 -> 53 | J27: 0 | K27: =MAX(0,I27-J27) -> 53 | L27: =COUNTIFS($A$2:$A$64,A27,$B$2:$B$64,B27,$K$2:$K$64,">"&K27)+1 -> 2 | M27: =IF(L27<=CEILING(COUNTIFS($A$2:$A$64,A27,$B$2:$B$64,B27)/2,1),"Pass","Fail") -> Pass | Q27: Annual report 2025 | R27: Annual report | S27: 2025 | T27: company website | U27: https://annualreport.dsm-firmenich.com/2025/_assets/downloads/entire-dsmfirmenich-iar25.pdf | V27: English | W27: 33840 | X27: Top half of Switzerland Materials; Creativity 3 from Perfumery & Beauty business unit creates fragrances for global and loc; red flag: none; Discloses internally substantiated discrimination and harassment cases; not a red flag under the rule.
A28: Switzerland | B28: Materials | C28: SIKA.SW | D28: Sika | E28: 1 | F28: 2 | G28: 2 | H28: 1 | I28: =E28/5*35+F28/5*30+G28/5*20+H28/5*15 -> 30 | J28: 0 | K28: =MAX(0,I28-J28) -> 30 | L28: =COUNTIFS($A$2:$A$64,A28,$B$2:$B$64,B28,$K$2:$K$64,">"&K28)+1 -> 3 | M28: =IF(L28<=CEILING(COUNTIFS($A$2:$A$64,A28,$B$2:$B$64,B28)/2,1),"Pass","Fail") -> Fail | Q28: Annual report 2025 | R28: Annual report | S28: 2025 | T28: company website | U28: https://www.sika.com/dam/dms/corporate/media/glo-ar-25-annual-report.pdf | V28: English | W28: 39707 | X28: Not in top half of Switzerland Materials; Cross-cultural 2 from Technical training and guidance for customers delivered in local langu; red flag: none; Discloses internally substantiated harassment cases; not a red flag under the rule.
A29: Taiwan | B29: Financials | C29: 2881.TW | D29: Fubon Financial | E29: 3 | F29: 3 | G29: 3 | H29: 2 | I29: =E29/5*35+F29/5*30+G29/5*20+H29/5*15 -> 57 | J29: 0 | K29: =MAX(0,I29-J29) -> 57 | L29: =COUNTIFS($A$2:$A$64,A29,$B$2:$B$64,B29,$K$2:$K$64,">"&K29)+1 -> 1 | M29: =IF(L29<=CEILING(COUNTIFS($A$2:$A$64,A29,$B$2:$B$64,B29)/2,1),"Pass","Fail") -> Pass | Q29: Annual report 2025 | R29: Annual report | S29: 2025 | T29: MOPS | U29: https://doc.twse.com.tw/pdf/2025_2881_20260612FE4_20261024_002816.pdf | V29: English | W29: 39709 | X29: Top half of Taiwan Financials; Cross-cultural 3 from Fubon Artistic Achievement Awards for the Disabled and All-Love Orches; red flag: none
A30: Taiwan | B30: Financials | C30: 2887.TW | D30: TS Financial Holding (formerly Taishin Financial Holdings) | E30: 3 | F30: 3 | G30: 3 | H30: 2 | I30: =E30/5*35+F30/5*30+G30/5*20+H30/5*15 -> 57 | J30: 0 | K30: =MAX(0,I30-J30) -> 57 | L30: =COUNTIFS($A$2:$A$64,A30,$B$2:$B$64,B30,$K$2:$K$64,">"&K30)+1 -> 1 | M30: =IF(L30<=CEILING(COUNTIFS($A$2:$A$64,A30,$B$2:$B$64,B30)/2,1),"Pass","Fail") -> Pass | Q30: Annual report 2025 | R30: Annual report | S30: 2025 | T30: MOPS | U30: https://doc.twse.com.tw/pdf/2025_2887_20260612FE4_20261024_001741.pdf | V30: English | W30: 23467 | X30: Top half of Taiwan Financials; Cross-cultural 3 from Nationwide ATM upgrade adding enlarged-font and barrier-free cardless ; red flag: none | Y30: TOC fallback (no usable table of contents): keyword paragraphs across the whole report; skipped 36 of 324 pages (risk, number pages, financial statements from page 325)
A31: Taiwan | B31: Financials | C31: 2883.TW | D31: KGI Financial Holding | E31: 2 | F31: 3 | G31: 2 | H31: 3 | I31: =E31/5*35+F31/5*30+G31/5*20+H31/5*15 -> 49 | J31: 0 | K31: =MAX(0,I31-J31) -> 49 | L31: =COUNTIFS($A$2:$A$64,A31,$B$2:$B$64,B31,$K$2:$K$64,">"&K31)+1 -> 3 | M31: =IF(L31<=CEILING(COUNTIFS($A$2:$A$64,A31,$B$2:$B$64,B31)/2,1),"Pass","Fail") -> Pass | Q31: Annual report 2025 | R31: Annual report | S31: 2025 | T31: MOPS | U31: https://doc.twse.com.tw/pdf/2025_2883_20260612FE4_20261024_002419.pdf | V31: English | W31: 27472 | X31: Top half of Taiwan Financials; Entrepreneurship 3 from 'Local Revitalizer+' program: skilled employee volunteers coach local ; red flag: none
A32: Taiwan | B32: Financials | C32: 2884.TW | D32: E.SUN Financial Holding | E32: 1 | F32: 3 | G32: 3 | H32: 3 | I32: =E32/5*35+F32/5*30+G32/5*20+H32/5*15 -> 46 | J32: 0 | K32: =MAX(0,I32-J32) -> 46 | L32: =COUNTIFS($A$2:$A$64,A32,$B$2:$B$64,B32,$K$2:$K$64,">"&K32)+1 -> 4 | M32: =IF(L32<=CEILING(COUNTIFS($A$2:$A$64,A32,$B$2:$B$64,B32)/2,1),"Pass","Fail") -> Fail | Q32: Annual report 2025 | R32: Annual report | S32: 2025 | T32: company website | U32: https://www.esunbank.com/en/-/media/ESUNFHC/Files/Investor-Relations/About-ESUN/Annual-Reports/Annual-Reports-FHC/esunfhc_annual_2025 | V32: English | W32: 40096 | X32: Not in top half of Taiwan Financials; Entrepreneurship 3 from Financial inclusion loan products, including micro-enterprise, young e; red flag: none
A33: Taiwan | B33: Financials | C33: 2890.TW | D33: Sinopac Financial Holdings | E33: 2 | F33: 3 | G33: 2 | H33: 2 | I33: =E33/5*35+F33/5*30+G33/5*20+H33/5*15 -> 46 | J33: 0 | K33: =MAX(0,I33-J33) -> 46 | L33: =COUNTIFS($A$2:$A$64,A33,$B$2:$B$64,B33,$K$2:$K$64,">"&K33)+1 -> 4 | M33: =IF(L33<=CEILING(COUNTIFS($A$2:$A$64,A33,$B$2:$B$64,B33)/2,1),"Pass","Fail") -> Fail | Q33: Annual report 2025 | R33: Annual report | S33: 2025 | T33: MOPS | U33: https://doc.twse.com.tw/pdf/2025_2890_20260526FE4_20261024_014510.pdf | V33: English | W33: 39921 | X33: Not in top half of Taiwan Financials; Community 3 from Company-wide employee training framework, including the SinoPac Univer; red flag: none
A34: Taiwan | B34: Financials | C34: 2885.TW | D34: Yuanta Financial Holding | E34: 2 | F34: 3 | G34: 2 | H34: 2 | I34: =E34/5*35+F34/5*30+G34/5*20+H34/5*15 -> 46 | J34: 0 | K34: =MAX(0,I34-J34) -> 46 | L34: =COUNTIFS($A$2:$A$64,A34,$B$2:$B$64,B34,$K$2:$K$64,">"&K34)+1 -> 4 | M34: =IF(L34<=CEILING(COUNTIFS($A$2:$A$64,A34,$B$2:$B$64,B34)/2,1),"Pass","Fail") -> Fail | Q34: Annual report 2025 | R34: Annual report | S34: 2025 | T34: company website | U34: https://www.yuanta.com/Files/970ac88b-be51-4dbd-8070-c3c680efcebe/YFH2025_E.pdf | V34: English | W34: 40186 | X34: Not in top half of Taiwan Financials; Community 3 from Yuanta Cultural and Educational Foundation runs a group-wide public we; red flag: none
A35: Taiwan | B35: Information Technology | C35: 2357.TW | D35: ASUS | E35: 3 | F35: 3 | G35: 3 | H35: 1 | I35: =E35/5*35+F35/5*30+G35/5*20+H35/5*15 -> 54 | J35: 0 | K35: =MAX(0,I35-J35) -> 54 | L35: =COUNTIFS($A$2:$A$64,A35,$B$2:$B$64,B35,$K$2:$K$64,">"&K35)+1 -> 1 | M35: =IF(L35<=CEILING(COUNTIFS($A$2:$A$64,A35,$B$2:$B$64,B35)/2,1),"Pass","Fail") -> Pass | Q35: Annual report 2025 | R35: Annual report | S35: 2025 | T35: company website | U35: https://www.asus.com/EVENT/Investor/Content/attachment_en/2025_Annual_Report_en.pdf | V35: English | W35: 30478 | X35: Top half of Taiwan Information Technology; Cross-cultural 3 from Sponsoring instructor fees for an art collective of autistic youth and; red flag: none; Discloses internally substantiated unspecified human rights risk incidents (harassment and workplace bullying handling described) cases; not a red flag under the rule.
A36: Taiwan | B36: Information Technology | C36: 2454.TW | D36: MediaTek | E36: 2 | F36: 3 | G36: 2 | H36: 2 | I36: =E36/5*35+F36/5*30+G36/5*20+H36/5*15 -> 46 | J36: 0 | K36: =MAX(0,I36-J36) -> 46 | L36: =COUNTIFS($A$2:$A$64,A36,$B$2:$B$64,B36,$K$2:$K$64,">"&K36)+1 -> 2 | M36: =IF(L36<=CEILING(COUNTIFS($A$2:$A$64,A36,$B$2:$B$64,B36)/2,1),"Pass","Fail") -> Pass | Q36: Annual report 2025 | R36: Annual report | S36: 2025 | T36: company website | U36: https://www.mediatek.com/hubfs/728015/MediaTek%20Assets/Pdfs/Annual%20Reports/2025-English-Annual-Report.pdf | V36: English | W36: 31141 | X36: Top half of Taiwan Information Technology; Community 3 from Nanzhou Sustainable Plan: sponsored education and culture program in a; red flag: none
A37: Taiwan | B37: Information Technology | C37: 2395.TW | D37: Advantech | E37: 2 | F37: 3 | G37: 2 | H37: 1 | I37: =E37/5*35+F37/5*30+G37/5*20+H37/5*15 -> 43 | J37: 0 | K37: =MAX(0,I37-J37) -> 43 | L37: =COUNTIFS($A$2:$A$64,A37,$B$2:$B$64,B37,$K$2:$K$64,">"&K37)+1 -> 3 | M37: =IF(L37<=CEILING(COUNTIFS($A$2:$A$64,A37,$B$2:$B$64,B37)/2,1),"Pass","Fail") -> Pass | Q37: Annual report 2025 | R37: Annual report | S37: 2025 | T37: MOPS | U37: https://doc.twse.com.tw/pdf/2025_2395_20260529FE4_20261024_015050.pdf | V37: English | W37: 30307 | X37: Top half of Taiwan Information Technology; Community 3 from Advantech Foundation funds arts and culture promotion, sustainable edu; red flag: none
A38: Taiwan | B38: Information Technology | C38: 3481.TW | D38: Innolux | E38: 2 | F38: 3 | G38: 2 | H38: 1 | I38: =E38/5*35+F38/5*30+G38/5*20+H38/5*15 -> 43 | J38: 0 | K38: =MAX(0,I38-J38) -> 43 | L38: =COUNTIFS($A$2:$A$64,A38,$B$2:$B$64,B38,$K$2:$K$64,">"&K38)+1 -> 3 | M38: =IF(L38<=CEILING(COUNTIFS($A$2:$A$64,A38,$B$2:$B$64,B38)/2,1),"Pass","Fail") -> Pass | Q38: Annual report 2025 | R38: Annual report | S38: 2025 | T38: MOPS | U38: https://doc.twse.com.tw/pdf/2025_3481_20260527FE4_20261024_015318.pdf | V38: English | W38: 37013 | X38: Top half of Taiwan Information Technology; Community 3 from Net Zero Education Walk Start Plan: environmental education courses an; red flag: none
A39: Taiwan | B39: Information Technology | C39: 3034.TW | D39: Novatek Microelectronics | E39: 2 | F39: 3 | G39: 2 | H39: 1 | I39: =E39/5*35+F39/5*30+G39/5*20+H39/5*15 -> 43 | J39: 0 | K39: =MAX(0,I39-J39) -> 43 | L39: =COUNTIFS($A$2:$A$64,A39,$B$2:$B$64,B39,$K$2:$K$64,">"&K39)+1 -> 3 | M39: =IF(L39<=CEILING(COUNTIFS($A$2:$A$64,A39,$B$2:$B$64,B39)/2,1),"Pass","Fail") -> Pass | Q39: Annual report 2025 | R39: Annual report | S39: 2025 | T39: company website | U39: https://www.novatek.com.tw/upload/website/_2025 Annual Report_e_26050614_856.pdf | V39: English | W39: 20252 | X39: Top half of Taiwan Information Technology; Community 3 from Novatek Educational Foundation scholarships for science education and ; red flag: none
A40: Taiwan | B40: Information Technology | C40: 3008.TW | D40: Largan Precision | E40: 0 | F40: 3 | G40: 1 | H40: 1 | I40: =E40/5*35+F40/5*30+G40/5*20+H40/5*15 -> 25 | J40: 0 | K40: =MAX(0,I40-J40) -> 25 | L40: =COUNTIFS($A$2:$A$64,A40,$B$2:$B$64,B40,$K$2:$K$64,">"&K40)+1 -> 6 | M40: =IF(L40<=CEILING(COUNTIFS($A$2:$A$64,A40,$B$2:$B$64,B40)/2,1),"Pass","Fail") -> Fail | Q40: Annual report 2025 | R40: Annual report | S40: 2025 | T40: company website | U40: https://www.largan.com.tw/en/tool-download/page_en_size/file/204/2025%20Company%20Annual%20Report | V40: English | W40: 13106 | X40: Not in top half of Taiwan Information Technology; Community 3 from Campus seminars held at schools to connect students with industry; red flag: none
A41: Taiwan | B41: Information Technology | C41: 2408.TW | D41: Nanya Technology | E41: 0 | F41: 3 | G41: 1 | H41: 1 | I41: =E41/5*35+F41/5*30+G41/5*20+H41/5*15 -> 25 | J41: 0 | K41: =MAX(0,I41-J41) -> 25 | L41: =COUNTIFS($A$2:$A$64,A41,$B$2:$B$64,B41,$K$2:$K$64,">"&K41)+1 -> 6 | M41: =IF(L41<=CEILING(COUNTIFS($A$2:$A$64,A41,$B$2:$B$64,B41)/2,1),"Pass","Fail") -> Fail | Q41: Annual report 2025 | R41: Annual report | S41: 2025 | T41: MOPS | U41: https://doc.twse.com.tw/pdf/2025_2408_20260521FE4_20261024_003738.pdf | V41: English | W41: 19704 | X41: Not in top half of Taiwan Information Technology; Community 3 from Partners with schools to deliver sustainability education to students; red flag: none
A42: Taiwan | B42: Information Technology | C42: 3443.TW | D42: Global Unichip Corp. | E42: 0 | F42: 2 | G42: 2 | H42: 1 | I42: =E42/5*35+F42/5*30+G42/5*20+H42/5*15 -> 23 | J42: 0 | K42: =MAX(0,I42-J42) -> 23 | L42: =COUNTIFS($A$2:$A$64,A42,$B$2:$B$64,B42,$K$2:$K$64,">"&K42)+1 -> 8 | M42: =IF(L42<=CEILING(COUNTIFS($A$2:$A$64,A42,$B$2:$B$64,B42)/2,1),"Pass","Fail") -> Fail | Q42: Annual report 2025 | R42: Annual report | S42: 2025 | T42: company website | U42: https://www.guc-asic.com/upload/2026_04_16/8_202604161551145dnuwxrHk5.pdf | V42: English | W42: 13129 | X42: Not in top half of Taiwan Information Technology; Cross-cultural 2 from On-site massage service staffed by visually impaired workers from a lo; red flag: none; Discloses internally substantiated harassment cases; not a red flag under the rule.
A43: Indonesia | B43: Communication Services | C43: EMTK.JK | D43: Elang Mahkota Teknologi | E43: 4 | F43: 2 | G43: 2 | H43: 3 | I43: =E43/5*35+F43/5*30+G43/5*20+H43/5*15 -> 57 | J43: 0 | K43: =MAX(0,I43-J43) -> 57 | L43: =COUNTIFS($A$2:$A$64,A43,$B$2:$B$64,B43,$K$2:$K$64,">"&K43)+1 -> 1 | M43: =IF(L43<=CEILING(COUNTIFS($A$2:$A$64,A43,$B$2:$B$64,B43)/2,1),"Pass","Fail") -> Pass | Q43: Annual report 2025 | R43: Annual report | S43: 2025 | T43: company website | U43: https://cms.emtek.co.id/media/annual_report_attachment_en/gcib/AR-EMTEK-2025.pdf | V43: Non-English | W43: 40150 | X43: Top half of Indonesia Communication Services; Creativity 4 from Operates leading free-to-air TV networks (SCTV, Indosiar, MOJI, Mentar; red flag: none; non-English source | Y43: E13: figure(s) not found near the quote, removed: 513.884
A44: Indonesia | B44: Communication Services | C44: TLK | D44: Telkom Indonesia | E44: 3 | F44: 3 | G44: 2 | H44: 2 | I44: =E44/5*35+F44/5*30+G44/5*20+H44/5*15 -> 53 | J44: 0 | K44: =MAX(0,I44-J44) -> 53 | L44: =COUNTIFS($A$2:$A$64,A44,$B$2:$B$64,B44,$K$2:$K$64,">"&K44)+1 -> 2 | M44: =IF(L44<=CEILING(COUNTIFS($A$2:$A$64,A44,$B$2:$B$64,B44)/2,1),"Pass","Fail") -> Pass | Q44: 20-F 2025 | R44: 20-F | S44: 2025 | T44: SEC EDGAR | U44: https://www.sec.gov/Archives/edgar/data/1001807/000110465926062051/tmb-20251231x20f.htm | V44: English | W44: 26124 | X44: Top half of Indonesia Communication Services; Creativity 3 from Dedicated digital content subsidiary (Nuon) running games, music and d; red flag: none
A45: Indonesia | B45: Communication Services | C45: DNET.JK | D45: Indoritel | E45: 0 | F45: 2 | G45: 1 | H45: 2 | I45: =E45/5*35+F45/5*30+G45/5*20+H45/5*15 -> 22 | J45: 0 | K45: =MAX(0,I45-J45) -> 22 | L45: =COUNTIFS($A$2:$A$64,A45,$B$2:$B$64,B45,$K$2:$K$64,">"&K45)+1 -> 3 | M45: =IF(L45<=CEILING(COUNTIFS($A$2:$A$64,A45,$B$2:$B$64,B45)/2,1),"Pass","Fail") -> Fail | Q45: Annual report 2025 | R45: Annual report | S45: 2025 | T45: company website | U45: https://www.indoritel.co.id/storage/files/pdf/AR%20Indoritel%202025_%20ok%20_1777368195.pdf | V45: Non-English | W45: 36476 | X45: Not in top half of Indonesia Communication Services; Entrepreneurship 2 from Indomaret (associate) gives local MSMEs access to sell their products ; red flag: none; non-English source
A46: Indonesia | B46: Consumer Staples | C46: AALI.JK | D46: Astra Agro Lestari | E46: 0 | F46: 3 | G46: 2 | H46: 3 | I46: =E46/5*35+F46/5*30+G46/5*20+H46/5*15 -> 35 | J46: 0 | K46: =MAX(0,I46-J46) -> 35 | L46: =COUNTIFS($A$2:$A$64,A46,$B$2:$B$64,B46,$K$2:$K$64,">"&K46)+1 -> 1 | M46: =IF(L46<=CEILING(COUNTIFS($A$2:$A$64,A46,$B$2:$B$64,B46)/2,1),"Pass","Fail") -> Pass | Q46: Annual report 2025 | R46: Annual report | S46: 2025 | T46: company website | U46: https://www.astra-agro.co.id/wp-content/uploads/2026/03/AR-2025-AALI-web.pdf | V46: Non-English | W46: 14524 | X46: Top half of Indonesia Consumer Staples; Entrepreneurship 3 from Village entrepreneurship programs, agricultural processing training, b; red flag: none; non-English source | Y46: E1: figure(s) not found near the quote, removed: 256, 230, 2,081 community: needs human review: figure(s) removed from cited evidence E1; the level may be lower entrepreneurship: needs human review: figure(s) removed from cited evidence E1; the level may be lower
A47: Indonesia | B47: Consumer Staples | C47: HMSP.JK | D47: Sampoerna | E47: 1 | F47: 3 | G47: 2 | H47: 3 | I47: =E47/5*35+F47/5*30+G47/5*20+H47/5*15 -> 42 | J47: 10 | K47: =MAX(0,I47-J47) -> 32 | L47: =COUNTIFS($A$2:$A$64,A47,$B$2:$B$64,B47,$K$2:$K$64,">"&K47)+1 -> 2 | M47: =IF(L47<=CEILING(COUNTIFS($A$2:$A$64,A47,$B$2:$B$64,B47)/2,1),"Pass","Fail") -> Pass | N47: tobacco | Q47: Annual report 2025 | R47: Annual report | S47: 2025 | T47: company website | U47: https://www.sampoerna.com/content/dam/pmicom/affiliates/sampoerna/docs/annua-report-and-sustainability-report-2025.pdf | V47: Non-English | W47: 39685 | X47: Top half of Indonesia Consumer Staples; Entrepreneurship 3 from Sampoerna Entrepreneurship Training Center (SETC) runs entrepreneurshi; red flag: tobacco; non-English source; Discloses internally substantiated unspecified compliance violations cases; not a red flag under the rule. | Y47: TOC fallback (chapters from the printed contents page hold only 601 words): keyword paragraphs across the whole report; skipped 98 of 491 pages (risk, number pages, financial statements from page 284, except 114 governance/sustainability page(s) after them)
A48: Indonesia | B48: Consumer Staples | C48: INDF.JK | D48: Indofood | E48: 1 | F48: 2 | G48: 2 | H48: 1 | I48: =E48/5*35+F48/5*30+G48/5*20+H48/5*15 -> 30 | J48: 0 | K48: =MAX(0,I48-J48) -> 30 | L48: =COUNTIFS($A$2:$A$64,A48,$B$2:$B$64,B48,$K$2:$K$64,">"&K48)+1 -> 3 | M48: =IF(L48<=CEILING(COUNTIFS($A$2:$A$64,A48,$B$2:$B$64,B48)/2,1),"Pass","Fail") -> Fail | Q48: Annual report 2025 | R48: Annual report | S48: 2025 | T48: company website | U48: https://www.indofood.com/uploads/annual/AR_ISM_2025_web.pdf | V48: Non-English | W48: 7550 | X48: Not in top half of Indonesia Consumer Staples; Cross-cultural 2 from Lactation rooms for breastfeeding mothers at operational units; red flag: none; non-English source | Y48: TOC fallback (chapters from the printed contents page hold only 1,079 words): keyword paragraphs across the whole report; skipped 167 of 298 pages (risk, number pages, financial statements from page 137)
A49: Indonesia | B49: Consumer Staples | C49: GGRM.JK | D49: Gudang Garam | E49: 2 | F49: 3 | G49: 1 | H49: 1 | I49: =E49/5*35+F49/5*30+G49/5*20+H49/5*15 -> 39 | J49: 10 | K49: =MAX(0,I49-J49) -> 29 | L49: =COUNTIFS($A$2:$A$64,A49,$B$2:$B$64,B49,$K$2:$K$64,">"&K49)+1 -> 4 | M49: =IF(L49<=CEILING(COUNTIFS($A$2:$A$64,A49,$B$2:$B$64,B49)/2,1),"Pass","Fail") -> Fail | N49: tobacco | Q49: Annual report 2025 | R49: Annual report | S49: 2025 | T49: company website | U49: https://www.gudanggaramtbk.com/media/uploads/files/GGRM_AR_2025_FINAL.pdf | V49: Non-English | W49: 17271 | X49: Not in top half of Indonesia Consumer Staples; Community 3 from Corporate social responsibility spending on education, infrastructure,; red flag: tobacco; non-English source
A50: Indonesia | B50: Financials | C50: BMRI.JK | D50: Bank Mandiri | E50: 2 | F50: 3 | G50: 3 | H50: 4 | I50: =E50/5*35+F50/5*30+G50/5*20+H50/5*15 -> 56 | J50: 0 | K50: =MAX(0,I50-J50) -> 56 | L50: =COUNTIFS($A$2:$A$64,A50,$B$2:$B$64,B50,$K$2:$K$64,">"&K50)+1 -> 1 | M50: =IF(L50<=CEILING(COUNTIFS($A$2:$A$64,A50,$B$2:$B$64,B50)/2,1),"Pass","Fail") -> Pass | Q50: Annual report 2025 | R50: Annual report | S50: 2025 | T50: company website | U50: https://www.bankmandiri.co.id/documents/38265486/0/%5BFINAL+-+2904%5D+ANNUAL+REPORT+BMRI+2025+%281%29.pdf/da87ca86-a02b-f394-b2e4-1ff3f268c0ee?t=1777514285182 | V50: English | W50: 40912 | X50: Top half of Indonesia Financials; Entrepreneurship 4 from Rumah BUMN centres providing training, capacity building and digitalis; red flag: none
A51: Indonesia | B51: Financials | C51: BBNI.JK | D51: Bank Negara Indonesia | E51: 2 | F51: 3 | G51: 3 | H51: 3 | I51: =E51/5*35+F51/5*30+G51/5*20+H51/5*15 -> 53 | J51: 0 | K51: =MAX(0,I51-J51) -> 53 | L51: =COUNTIFS($A$2:$A$64,A51,$B$2:$B$64,B51,$K$2:$K$64,">"&K51)+1 -> 2 | M51: =IF(L51<=CEILING(COUNTIFS($A$2:$A$64,A51,$B$2:$B$64,B51)/2,1),"Pass","Fail") -> Fail | Q51: Annual report 2025 | R51: Annual report | S51: 2025 | T51: company website | U51: https://www.bni.co.id/Portals/1/BNI/Perusahaan/HubunganInvestor/Docs/BNI-AR-2025-IND.pdf | V51: Non-English | W51: 41096 | X51: Not in top half of Indonesia Financials; Entrepreneurship 3 from Rumah BUMN centres providing training, coaching and licensing help to ; red flag: none; non-English source | Y51: E11: figure(s) not found near the quote, removed: 013 cross_cultural: needs human review: figure(s) removed from cited evidence E11; the level may be lower TOC fallback (no usable table of contents): keyword paragraphs across the whole report; skipped 153 of 1602 pages (risk, number pages, financial statements from page 685, except 876 governance/sustainability page(s) after them)
A52: Singapore | B52: Financials | C52: U11.SI | D52: UOB | E52: 3 | F52: 3 | G52: 2 | H52: 2 | I52: =E52/5*35+F52/5*30+G52/5*20+H52/5*15 -> 53 | J52: 0 | K52: =MAX(0,I52-J52) -> 53 | L52: =COUNTIFS($A$2:$A$64,A52,$B$2:$B$64,B52,$K$2:$K$64,">"&K52)+1 -> 1 | M52: =IF(L52<=CEILING(COUNTIFS($A$2:$A$64,A52,$B$2:$B$64,B52)/2,1),"Pass","Fail") -> Pass | Q52: Annual report 2025 | R52: Annual report | S52: 2025 | T52: company website | U52: https://www.uobgroup.com/investor-relations/assets/pdfs/investor/annual/uob-annual-report-2025.pdf | V52: English | W52: 17222 | X52: Top half of Singapore Financials; Creativity 3 from Runs the UOB Painting of the Year and UOB Art in Ink Awards, regional ; red flag: none
A53: Singapore | B53: Financials | C53: O39.SI | D53: OCBC Bank | E53: 2 | F53: 3 | G53: 3 | H53: 2 | I53: =E53/5*35+F53/5*30+G53/5*20+H53/5*15 -> 50 | J53: 0 | K53: =MAX(0,I53-J53) -> 50 | L53: =COUNTIFS($A$2:$A$64,A53,$B$2:$B$64,B53,$K$2:$K$64,">"&K53)+1 -> 2 | M53: =IF(L53<=CEILING(COUNTIFS($A$2:$A$64,A53,$B$2:$B$64,B53)/2,1),"Pass","Fail") -> Pass | Q53: Annual report 2025 | R53: Annual report | S53: 2025 | T53: company website | U53: https://www.ocbc.com/iwov-resources/sg/ocbc/gbc/pdf/investors/annual-reports/2025/2025-annual-report-en.pdf | V53: English | W53: 7072 | X53: Top half of Singapore Financials; Cross-cultural 3 from Dialect-speaking branch ambassadors for seniors and accessible app tex; red flag: none | Y53: TOC fallback (no usable table of contents): keyword paragraphs across the whole report; skipped 193 of 276 pages (risk, number pages, financial statements from page 97)
A54: Singapore | B54: Financials | C54: D05.SI | D54: DBS Group | E54: 1 | F54: 4 | G54: 3 | H54: 2 | I54: =E54/5*35+F54/5*30+G54/5*20+H54/5*15 -> 49 | J54: 0 | K54: =MAX(0,I54-J54) -> 49 | L54: =COUNTIFS($A$2:$A$64,A54,$B$2:$B$64,B54,$K$2:$K$64,">"&K54)+1 -> 3 | M54: =IF(L54<=CEILING(COUNTIFS($A$2:$A$64,A54,$B$2:$B$64,B54)/2,1),"Pass","Fail") -> Pass | Q54: Annual report 2025 | R54: Annual report | S54: 2025 | T54: company website | U54: https://www.dbs.com/annualreports/2025/i/pdf/dbs-ar-2025.pdf | V54: English | W54: 36346 | X54: Top half of Singapore Financials; Community 4 from DBS Foundation programmes and partnerships supporting vulnerable commu; red flag: none
A55: Singapore | B55: Financials | C55: S68.SI | D55: Singapore Exchange | E55: 1 | F55: 3 | G55: 2 | H55: 1 | I55: =E55/5*35+F55/5*30+G55/5*20+H55/5*15 -> 36 | J55: 0 | K55: =MAX(0,I55-J55) -> 36 | L55: =COUNTIFS($A$2:$A$64,A55,$B$2:$B$64,B55,$K$2:$K$64,">"&K55)+1 -> 4 | M55: =IF(L55<=CEILING(COUNTIFS($A$2:$A$64,A55,$B$2:$B$64,B55)/2,1),"Pass","Fail") -> Fail | Q55: Annual report 2025 | R55: Annual report | S55: 2025 | T55: company website | U55: https://links.sgx.com/FileOpen/2025_SGX_Annual_Report.ashx?App=Announcement&FileID=859054 | V55: English | W55: 18020 | X55: Not in top half of Singapore Financials; Community 3 from SGX Cares Bull Charge, an annual fundraising programme (Charity Run, C; red flag: none
A56: Singapore | B56: Financials | C56: P15.SI | D56: Pacific Century Regional Developments | E56: 2 | F56: 2 | G56: 1 | H56: 0 | I56: =E56/5*35+F56/5*30+G56/5*20+H56/5*15 -> 30 | J56: 0 | K56: =MAX(0,I56-J56) -> 30 | L56: =COUNTIFS($A$2:$A$64,A56,$B$2:$B$64,B56,$K$2:$K$64,">"&K56)+1 -> 5 | M56: =IF(L56<=CEILING(COUNTIFS($A$2:$A$64,A56,$B$2:$B$64,B56)/2,1),"Pass","Fail") -> Fail | Q56: Annual report 2025 | R56: Annual report | S56: 2025 | T56: SGX company announcements | U56: https://links.sgx.com/1.0.0/corporate-announcements/44JTWA0DH7EZYK4P/881221_PCRDL_Annual%20Report%202025.pdf | V56: English | W56: 5136 | X56: Not in top half of Singapore Financials; Creativity 2 from Artiste management and live-event business at major associate PCCW (Vi; red flag: none | Y56: TOC fallback (chapters from the printed contents page hold only 1,362 words): keyword paragraphs across the whole report; skipped 35 of 120 pages (risk, number pages, financial statements from page 41, except 49 governance/sustainability page(s) after them)
A57: Singapore | B57: Industrials | C57: S58.SI | D57: SATS | E57: 1 | F57: 3 | G57: 2 | H57: 1 | I57: =E57/5*35+F57/5*30+G57/5*20+H57/5*15 -> 36 | J57: 0 | K57: =MAX(0,I57-J57) -> 36 | L57: =COUNTIFS($A$2:$A$64,A57,$B$2:$B$64,B57,$K$2:$K$64,">"&K57)+1 -> 1 | M57: =IF(L57<=CEILING(COUNTIFS($A$2:$A$64,A57,$B$2:$B$64,B57)/2,1),"Pass","Fail") -> Pass | Q57: Annual report 2026 | R57: Annual report | S57: 2026 | T57: SGX company announcements | U57: https://links.sgx.com/1.0.0/corporate-announcements/KDUEMRFCNK9XYXB6/895114_SATS_Annual_Report_FY2026.pdf | V57: English | W57: 7344 | X57: Top half of Singapore Industrials; Community 3 from SATS Foundation funds registered charity programmes in Singapore, main; red flag: none | Y57: TOC fallback (chapters from the printed contents page hold only 3,244 words): keyword paragraphs across the whole report; skipped 34 of 121 pages (risk, number pages, financial statements from page 94)
A58: Singapore | B58: Industrials | C58: C6L.SI | D58: Singapore Airlines | E58: 1 | F58: 3 | G58: 2 | H58: 1 | I58: =E58/5*35+F58/5*30+G58/5*20+H58/5*15 -> 36 | J58: 0 | K58: =MAX(0,I58-J58) -> 36 | L58: =COUNTIFS($A$2:$A$64,A58,$B$2:$B$64,B58,$K$2:$K$64,">"&K58)+1 -> 1 | M58: =IF(L58<=CEILING(COUNTIFS($A$2:$A$64,A58,$B$2:$B$64,B58)/2,1),"Pass","Fail") -> Pass | Q58: Annual report 2025 | R58: Annual report | S58: 2025 | T58: SGX company announcements | U58: https://links.sgx.com/1.0.0/corporate-announcements/CBBHM38X24NO0DHG/894198_Annual%20Report%20FY2025-26.pdf | V58: English | W58: 12662 | X58: Top half of Singapore Industrials; Community 3 from Singapore Airlines Foundation runs two flagship youth programmes (Yout; red flag: none
A59: Singapore | B59: Industrials | C59: BN4.SI | D59: Keppel | E59: 0 | F59: 3 | G59: 1 | H59: 1 | I59: =E59/5*35+F59/5*30+G59/5*20+H59/5*15 -> 25 | J59: 0 | K59: =MAX(0,I59-J59) -> 25 | L59: =COUNTIFS($A$2:$A$64,A59,$B$2:$B$64,B59,$K$2:$K$64,">"&K59)+1 -> 3 | M59: =IF(L59<=CEILING(COUNTIFS($A$2:$A$64,A59,$B$2:$B$64,B59)/2,1),"Pass","Fail") -> Fail | Q59: Annual report 2025 | R59: Annual report | S59: 2025 | T59: SGX company announcements | U59: https://links.sgx.com/1.0.0/corporate-announcements/CMLEN559K1LSH1QR/880492_1.%20Keppel%20Ltd._Annual%20Report%202025.pdf | V59: English | W59: 8699 | X59: Not in top half of Singapore Industrials; Community 3 from Social investment spending, including grants disbursed through the com; red flag: none | Y59: TOC fallback (no usable table of contents): keyword paragraphs across the whole report; skipped 146 of 245 pages (risk, number pages, financial statements from page 105)
A60: Singapore | B60: Industrials | C60: NS8U.SI | D60: Hutchison Port Holdings Trust | E60: 0 | F60: 2 | G60: 2 | H60: 1 | I60: =E60/5*35+F60/5*30+G60/5*20+H60/5*15 -> 23 | J60: 0 | K60: =MAX(0,I60-J60) -> 23 | L60: =COUNTIFS($A$2:$A$64,A60,$B$2:$B$64,B60,$K$2:$K$64,">"&K60)+1 -> 4 | M60: =IF(L60<=CEILING(COUNTIFS($A$2:$A$64,A60,$B$2:$B$64,B60)/2,1),"Pass","Fail") -> Fail | Q60: Annual report 2025 | R60: Annual report | S60: 2025 | T60: SGX company announcements | U60: https://links.sgx.com/1.0.0/corporate-announcements/NJVPQZT3VFNIX7HM/882457_HPHT%20AR2025%20SGX.pdf | V60: English | W60: 39506 | X60: Not in top half of Singapore Industrials; Cross-cultural 2 from Gold sponsorship of and employee participation in a disability-inclusi; red flag: none
A61: Singapore | B61: Real Estate | C61: C38U.SI | D61: CapitaLand Integrated Commercial Trust | E61: 2 | F61: 2 | G61: 2 | H61: 0 | I61: =E61/5*35+F61/5*30+G61/5*20+H61/5*15 -> 34 | J61: 0 | K61: =MAX(0,I61-J61) -> 34 | L61: =COUNTIFS($A$2:$A$64,A61,$B$2:$B$64,B61,$K$2:$K$64,">"&K61)+1 -> 1 | M61: =IF(L61<=CEILING(COUNTIFS($A$2:$A$64,A61,$B$2:$B$64,B61)/2,1),"Pass","Fail") -> Pass | P61: community, cross-cultural | Q61: Annual report 2025 | R61: Annual report | S61: 2025 | T61: SGX company announcements | U61: https://links.sgx.com/1.0.0/corporate-announcements/PY3VCKEQ8KS6R716/878885_2_CICT%20AR%202025_Final.pdf | V61: English | W61: 8649 | X61: Top half of Singapore Real Estate; Cross-cultural 2 from Properties built to and certified under Singapore's BCA Universal Desi; red flag: none | Y61: coverage insufficient (community, cross_cultural); second look: no standalone report found TOC fallback (chapters from the pdf bookmarks (all levels) hold only 3,622 words): keyword paragraphs across the whole report; skipped 109 of 199 pages (risk, number pages, financial statements from page 97)
A62: Singapore | B62: Real Estate | C62: K71U.SI | D62: Keppel REIT | E62: 0 | F62: 2 | G62: 2 | H62: 0 | I62: =E62/5*35+F62/5*30+G62/5*20+H62/5*15 -> 20 | J62: 0 | K62: =MAX(0,I62-J62) -> 20 | L62: =COUNTIFS($A$2:$A$64,A62,$B$2:$B$64,B62,$K$2:$K$64,">"&K62)+1 -> 2 | M62: =IF(L62<=CEILING(COUNTIFS($A$2:$A$64,A62,$B$2:$B$64,B62)/2,1),"Pass","Fail") -> Pass | Q62: Annual report 2025 | R62: Annual report | S62: 2025 | T62: company website | U62: https://www.keppelreit.com/file/investor-relations/publications/annual-reports/keppel-reit-ar25.pdf | V62: English | W62: 12499 | X62: Top half of Singapore Real Estate; Cross-cultural 2 from Training on unconscious bias and inclusive leadership for employees; red flag: none | Y62: TOC fallback (no usable table of contents): keyword paragraphs across the whole report; skipped 79 of 228 pages (risk, number pages, financial statements from page 112, except 48 governance/sustainability page(s) after them)
A63: Singapore | B63: Real Estate | C63: A17U.SI | D63: CapitaLand Ascendas REIT | E63: 0 | F63: 2 | G63: 1 | H63: 0 | I63: =E63/5*35+F63/5*30+G63/5*20+H63/5*15 -> 16 | J63: 0 | K63: =MAX(0,I63-J63) -> 16 | L63: =COUNTIFS($A$2:$A$64,A63,$B$2:$B$64,B63,$K$2:$K$64,">"&K63)+1 -> 3 | M63: =IF(L63<=CEILING(COUNTIFS($A$2:$A$64,A63,$B$2:$B$64,B63)/2,1),"Pass","Fail") -> Fail | P63: community, cross-cultural | Q63: Annual report 2025 | R63: Annual report | S63: 2025 | T63: SGX company announcements | U63: https://links.sgx.com/1.0.0/corporate-announcements/VLMUR6L61OAEVKHB/881419_CLAR%20-%20AR%202025.pdf | V63: English | W63: 5086 | X63: Not in top half of Singapore Real Estate; Community 2 from Training provided to the Manager's employees; red flag: none | Y63: coverage insufficient (community, cross_cultural); second look: no standalone report found TOC fallback (chapters from the printed contents page hold only 2,823 words): keyword paragraphs across the whole report; skipped 118 of 212 pages (risk, number pages, financial statements from page 110)
A64: Singapore | B64: Real Estate | C64: BUOU.SI | D64: Frasers Logistics & Commercial Trust | E64: 0 | F64: 2 | G64: 1 | H64: 0 | I64: =E64/5*35+F64/5*30+G64/5*20+H64/5*15 -> 16 | J64: 0 | K64: =MAX(0,I64-J64) -> 16 | L64: =COUNTIFS($A$2:$A$64,A64,$B$2:$B$64,B64,$K$2:$K$64,">"&K64)+1 -> 3 | M64: =IF(L64<=CEILING(COUNTIFS($A$2:$A$64,A64,$B$2:$B$64,B64)/2,1),"Pass","Fail") -> Fail | P64: community | Q64: Annual report 2025 + standalone sustainability report (half weight) | R64: Annual report | S64: 2025 | T64: SGX company announcements | U64: https://links.sgx.com/1.0.0/corporate-announcements/531D1L1A4ZGIBBAO/870400_FLCT%20-%20Annual%20Report%202025.pdf | V64: English | W64: 13632 | X64: Not in top half of Singapore Real Estate; Community 2 from Employee-led community initiatives, including partnerships with the Re; red flag: none
A66: Blue = inputs from the AI scoring after the code's quote checks (theme scores 0-5; red flag deduction = 10 points per verified red flag). Black = formulas.
A67: Alignment = Creativity/5×35 + Community/5×30 + Cross-cultural/5×20 + Entrepreneurship/5×15. Final = Alignment − red flag deduction (not below 0).
A68: Rank = 1 + companies in the same country-sector with a higher final score (ties share a rank). Pass = rank within the top half: rank ≤ ceil(n/2), n = scored companies in the country-sector.
A69: Decimal theme scores (e.g. 2.5) come from the half-weight rule: standalone sustainability-report evidence counts at half weight. Third component: not decided yet (blank).

Sheet Evidence quotes
A1: Country | B1: Sector | C1: Ticker | D1: Company | E1: Type | F1: Themes / flag | G1: Activity | H1: Quote (word for word, checked by code) | I1: English translation | J1: Section | K1: Source
A2: Denmark | B2: Financials | C2: ALSYDB.CO | D2: AL Sydbank A/S | E2: Evidence | F2: community: external_education | G2: Employees visit schools nationwide during Money Week to teach financial literacy classes | H2: During this week employees from AL Sydbank visit schools throughout the country to teach classes in financial literacy. | J2: Annual report > S – Social Information > AL Sydbank’s employees > Focus on personal finances during Money Week | K2: filing
A3: Denmark | B3: Financials | C3: ALSYDB.CO | D3: AL Sydbank A/S | E3: Evidence | F3: cross_cultural: internal_practice | G3: Workplace aids for employees with special needs | H3: In addition the health and safety manual contains a description of various aids for employees with special needs. | J3: Annual report > S – Social Information > Well-being and security for employees | K3: filing
A4: Denmark | B4: Financials | C4: ALSYDB.CO | D4: AL Sydbank A/S | E4: Evidence | F4: cross_cultural: demographics_only | G4: Gender balance target for management positions met in 2025 | H4: AL Sydbank’s overall objective is to achieve an equal gender balance among all managers and in 2025 we achieved the subtarget that the underrepresented gender will account for at least 35% of all employees in management positions in 2025. | J4: Annual report > S – Social Information > Diversity | K4: filing
A5: Denmark | B5: Financials | C5: ALSYDB.CO | D5: AL Sydbank A/S | E5: Evidence | F5: community: employee_development | G5: Competence mapping and talent development initiative for employees | H5: In 2025 determined efforts were made at AL Sydbank to identify employees’ competences and build the foundations for talent development. | J5: Annual report > S – Social Information > AL Sydbank’s employees > Talent development | K5: filing
A6: Denmark | B6: Financials | C6: ALSYDB.CO | D6: AL Sydbank A/S | E6: Evidence | F6: community: employee_development | G6: Regional trust-building communication project with additional adviser training | H6: Advisers receive additional training in customer contact in order to strengthen their relationship with customers and ensure that advice is based on trust, understanding and being present. | J6: Annual report > S – Social Information > Trust-building communication as a strategic project | K6: filing
A7: Denmark | B7: Financials | C7: ALSYDB.CO | D7: AL Sydbank A/S | E7: Evidence | F7: community: external_education | G7: Public 'Stop svindlerne' events teaching people to protect themselves against financial fraud | H7: AL Sydbank organises “Stop svindlerne” (Stop the fraudsters) events regularly where participants can learn how to protect themselves against financial fraud. | J7: Annual report > S – Social Information > Fighting crime > Efforts to combat IT fraud | K7: filing
A8: Denmark | B8: Financials | C8: ALSYDB.CO | D8: AL Sydbank A/S | E8: Evidence | F8: community: community_investment | G8: Sponsorships of clubs, associations, students and unions nationwide, mainly team and grassroots sports | H8: AL Sydbank supports via sponsorships small and large clubs and associations, students and unions across the country – primarily within team sports and grassroot sports. | J8: Annual report > Business model > Local presence > Local support | K8: filing
A9: Denmark | B9: Financials | C9: ALSYDB.CO | D9: AL Sydbank A/S | E9: Evidence | F9: community: community_investment | G9: Donations to charitable cultural, popular and educational purposes through several affiliated foundations | H9: AL Sydbank makes donations to charitable cultural, popular and educational purposes via the charitable foundations the Sydbank Foundation, Arbejdernes Landsbanks Fond, Trelleborg Fonden, Den Jyske Sparekasses Støttefonde, Jelling Sparekasses Fond, Fonden for Sparekassen Farsø as well as Fonden for Sparekassen i Skals. | J9: Annual report > Business model > Local presence > Local support | K9: filing
A10: Denmark | B10: Financials | C10: ALSYDB.CO | D10: AL Sydbank A/S | E10: Evidence | F10: community: community_investment | G10: Proposed donation to the Sydbank Foundation, subject to the annual general meeting | H10: The Board of Directors will propose to the annual general meeting that a dividend of DKK 25 per share, totalling DKK 2,145m, be distributed and that DKK 18m be donated to the Sydbank Foundation. | J10: Annual report > Financial review > Proposed dividend | K10: filing
A11: Denmark | B11: Financials | C11: ALSYDB.CO | D11: AL Sydbank A/S | E11: Evidence | F11: cross_cultural: customer_access | G11: Dedicated Sunflower phone line where trained staff assist customers with special needs | H11: For instance, in 2025 we set up a special Sunflower line where customers are assisted by employees who are mindful that these customers have special needs. | J11: Annual report > S – Social Information > Digitalisation | K11: filing
A12: Denmark | B12: Financials | C12: ALSYDB.CO | D12: AL Sydbank A/S | E12: Evidence | F12: cross_cultural: customer_access | G12: Digital banking platforms adapted for visually and hearing impaired customers | H12: We have also developed our digital platforms so that greater consideration is given to the visually impaired and the hearing impaired. | J12: Annual report > S – Social Information > Digitalisation | K12: filing
A13: Denmark | B13: Financials | C13: ALSYDB.CO | D13: AL Sydbank A/S | E13: Evidence | F13: cross_cultural: customer_access | G13: Free cash deposits and withdrawals for all retail clients with a NemKonto account | H13: This also means that all retail clients with a NemKonto account at our bank have the possibility to deposit and withdraw money free of charge. | J13: Annual report > Business model > The Bank’s customers | K13: filing
... A28: Denmark | B28: Financials | C28: DANSKE.CO | D28: Danske Bank | E28: Internal finding (no deduction) | F28: rights_finding (found by: internal) | G28: Internal whistleblowing reports of discrimination, bullying or harassment logged in 2025. The report does not say how many were substantiated. It states no material fines, penalties or severe human rights incidents, and no outside finding. Recorded for the team's note only; it costs no points. | H28: In terms of incidents and complaints reported through our whistleblowing system, 26 incidents related to discrimination within the Group’s workforce were logged in 2025 (2024: 16 incidents). | J28: Annual report > Sustainability Statement > Own workforce > Culture and Engagement Survey (CES) | K28: filing
A29: Denmark | B29: Financials | C29: DJUR.CO | D29: Djurslands Bank A/S | E29: Evidence | F29: community: employee_development | G29: Structured professional and personal skills development for all employees, with job profiles, personal development plans and at least four yearly development meetings (SUM) | H29: Banken arbejder systematiseret med faglig og personlig kompetenceudvikling af de enkelte medarbejdere. | I29: The bank works systematically with the professional and personal skills development of individual employees. | J29: Annual report > Ledelsesberetning > Forretningsmodel og strategi > Medarbejdere | K29: filing
A30: Denmark | B30: Financials | C30: DJUR.CO | D30: Djurslands Bank A/S | E30: Evidence | F30: community: external_education | G30: Takes in financial economist and finance bachelor students as interns every year, leading toward trainee positions | H30: Djurslands Bank prioriterer højt at tage ansvar for at uddanne fremtidens bankmedarbejdere, og vi tager hvert år imod finansøkonom- og finansbachelorstuderende i praktik. | I30: Djurslands Bank gives high priority to taking responsibility for educating future bank employees, and every year we take in financial economist and finance bachelor students as interns. | J30: Annual report > Ledelsesberetning > Forretningsmodel og strategi > Strategiske kundegrupper > For unge, af unge | K30: filing
A31: Denmark | B31: Financials | C31: DJUR.CO | D31: Djurslands Bank A/S | E31: Evidence | F31: community: community_investment | G31: Sponsors local activities and associations, including naming sponsorships of sports arenas in four towns and main sponsorship of a handball club | H31: Vi er aktive i lokalsamfundet og støtter synligt lokale aktiviteter og foreninger. | I31: We are active in the local community and visibly support local activities and associations. | J31: Annual report > Ledelsesberetning > Samfundsansvar > Lokalsamfundet | K31: filing
A32: Denmark | B32: Financials | C32: DJUR.CO | D32: Djurslands Bank A/S | E32: Evidence | F32: cross_cultural: internal_practice | G32: Statutory gender-balance measures, including extra focus on the career wishes of employees of the underrepresented gender in the annual development talk | H32: Der vil for det underrepræsenterede køns medarbejdere være ekstra fokus på området ”Hvilke udfordringer ønsker du i fremtiden?” i den årlige udviklingssamtale. | I32: For employees of the underrepresented gender there will be extra focus on the topic 'Which challenges do you want in the future?' in the annual development talk. | J32: Annual report > Ledelsesberetning > Selskabsledelse > Kønsfordeling | K32: filing
A33: Denmark | B33: Financials | C33: DJUR.CO | D33: Djurslands Bank A/S | E33: Evidence | F33: entrepreneurship: serving | G33: Ordinary banking services for business customers, including SMEs | H33: Banken rådgiver og servicerer 64.962 private kunder og 5.536 erhvervsvirksomheder og offentlige institutioner, samt 1.170 foreningskunder. | I33: The bank advises and serves 64,962 private customers and 5,536 businesses and public institutions, as well as 1,170 association customers. | J33: Annual report > Ledelsesberetning > Forretningsmodel og strategi > Kunder | K33: filing
A34: Denmark | B34: Financials | C34: JYSK.CO | D34: Jyske Bank | E34: Evidence | F34: community: employee_development | G34: Additional sustainability-transition training offered to a significant share of customer-facing employees | H34: As part of Jyske Bank’s efforts to combat climate change, a significant share of customer-oriented employees are offered additional training, to help them enter the dialogue with and advise our customers on sustainable transition. | J34: Annual report > Sustainability > S1 Own workforce > Training and skills enhancement further develop employees | K34: filing
A35: Denmark | B35: Financials | C35: JYSK.CO | D35: Jyske Bank | E35: Evidence | F35: community: employee_development | G35: Training programme completed by all employee union representatives | H35: A total of 106 employees serve as union representatives, and they have all completed a training programme to be equipped for carrying out their duties. | J35: Annual report > Sustainability > S1 Own workforce > Finansforbundet, Jyske Bank Kreds | K35: filing
A36: Denmark | B36: Financials | C36: JYSK.CO | D36: Jyske Bank | E36: Evidence | F36: community: community_investment | G36: Ongoing involvement with and support for the Danish Finance Institute, an independent research institute in finance and economics | H36: Jyske Bank has been actively involved with the Danish Finance Institute (DFI) since its foundation in 2017 as part of our commitment to strengthening the financial sector in Denmark. | J36: Annual report > Sustainability > S1 Own workforce > Support for research in economics and finance | K36: filing
A37: Denmark | B37: Financials | C37: JYSK.CO | D37: Jyske Bank | E37: Evidence | F37: cross_cultural: customer_access | G37: Participation in the Sunflower programme to support customers with invisible disabilities, also included as a mandatory employee learning activity | H37: Jyske Bank remains part of the Sunflower programme, which helps to ensure a good customer experience for everyone, including customers who have an invisible disability. | J37: Annual report > Sustainability > S4 Consumers and end-users > The Sunflower programme | K37: filing
A38: Denmark | B38: Financials | C38: JYSK.CO | D38: Jyske Bank | E38: Evidence | F38: cross_cultural: customer_access | G38: Accessibility improvements to online banking, apps and documents, including testing with a visually impaired customer | H38: Jyske Bank is actively working to improve accessibility in its digital self-service solutions, so that all customers – regardless of any functional impairment – have equal access to online banking, apps and documents. | J38: Annual report > Sustainability > S4 Consumers and end-users > Accessibility and user involvement in digital solutions | K38: filing
A39: Denmark | B39: Financials | C39: JYSK.CO | D39: Jyske Bank | E39: Evidence | F39: cross_cultural: internal_practice | G39: Gender-balanced recruitment practice requiring both genders in first-round interviews | H39: In 2025, we succeeded in having both genders represented in 53% of interviews. | J39: Annual report > Sustainability > S1 Own workforce > Gender diversity | K39: filing
A40: Denmark | B40: Health Care | C40: CHEMM.CO | D40: ChemoMetec | E40: Evidence | F40: community: employee_development | G40: General development, training and upskilling offered to employees | H40: We also offer our employees decent and attractive working and employment conditions as well as regular development, training and upgrading of skills to ensure that they are able to meet the ever-increasing labour market demands and to help deliver on ChemoMetec’s strategy. | J40: Annual report > Sustainability > Social, employee-related and diversity matters | K40: filing
A41: Denmark | B41: Health Care | C41: CHEMM.CO | D41: ChemoMetec | E41: Evidence | F41: community: employee_development | G41: Ongoing specialist training for sales staff on automation and integrated solutions | H41: Selling our solutions requires a high level of technical expertise as well as an understanding of our customers’ operations, and as we increasingly focus on automation and integrated solutions, we are investing in specialist training for our staff on an ongoing basis. | J41: Annual report > Our business model > Specialised sales force and support | K41: filing
A42: Denmark | B42: Health Care | C42: CHEMM.CO | D42: ChemoMetec | E42: Evidence | F42: cross_cultural: demographics_only | G42: Disclosure of management-team gender composition | H42: At the end of the 2025/26 financial year, the Management team had 76% male and 24% female members. | J42: Annual report > Sustainability > Diversity on the Board of Directors and other management levels > Other management levels | K42: filing
A43: Denmark | B43: Health Care | C43: CHEMM.CO | D43: ChemoMetec | E43: Evidence | F43: entrepreneurship: serving | G43: Placing cell counting instruments with business incubators to build a position in the start-up segment | H43: Over a number of years, ChemoMetec has built an attractive market position in this segment by placing our instruments with incubators, and the focus is now on leveraging the new opportunities in the segment. | J43: Annual report > Performance in 2025/26 > Business performance > Business area 1 (LCB market) | K43: filing
A44: Denmark | B44: Health Care | C44: BAVA.CO | D44: Bavarian Nordic | E44: Evidence | F44: community: community_investment | G44: In-kind donation of mpox vaccine doses to Africa CDC and UNICEF for outbreak response in Uganda and Liberia | H44: As part of our partnership with African CDC and UNICEF, Bavarian Nordic has donated a total of 130,000 doses of our mpox vaccine to help strengthen outbreak response. | J44: Annual report > Sustainability statements > S4 Consumers and end-users > Access to vaccines > Action 1 > Donations | K44: filing
A45: Denmark | B45: Health Care | C45: BAVA.CO | D45: Bavarian Nordic | E45: Evidence | F45: cross_cultural: customer_access | G45: Lowest-price mpox vaccine access for low- and lower-middle-income countries through Gavi and UNICEF agreements | H45: Through these contracts, we have worked together with all aforementioned parties to ensure vaccine access with the lowest price for the 77 low- and lower-middle-income countries. | J45: Annual report > Sustainability statements > S4 Consumers and end-users > Access to vaccines > Action 1 > Mpox: Working with partners to reach populations in low- and lower-middle-income countries | K45: filing
... A434: Indonesia | B434: Communication Services | C434: TLK | D434: Telkom Indonesia | E434: Evidence | F434: cross_cultural: internal_practice | G434: DayCare facilities and Srikandi Telkom gender-inclusion program | H434: In 2025, women represented 23.2% of managerial positions in our Group, supported by our DayCare facilities and the Srikandi Telkom program to promote gender inclusion. | J434: Item 4.B > ESG Matters > Social Responsibility > Workplace Environment and Employee Support | K434: filing
A435: Indonesia | B435: Communication Services | C435: DNET.JK | D435: Indoritel | E435: Evidence | F435: community: employee_development | G435: Training and competency development programs for the company's own employees | H435: Sepanjang tahun 2025, Perseroan telah memfasilitasi karyawan dengan berbagai pelatihan sebagai berikut: | I435: Throughout 2025, the Company facilitated employees with various training programs as follows: | J435: Annual report > Sustainability Report > Social Performance > Competency Development [IDX S.05] | K435: filing
A436: Indonesia | B436: Communication Services | C436: DNET.JK | D436: Indoritel | E436: Evidence | F436: community: community_investment | G436: ROTI (associate) donations to disaster-affected communities | H436: Bantuan kepada masyarakat yang tertimpa bencana serta masyarakat yang menjadi korban banjir bandang dan tanah longsor. | I436: Donations to support communities affected by disasters, as well as those affected by flash floods and landslides. | J436: Annual report > Sustainability Report > CSR Activities in 2025 > ROTI > Natural Disaster | K436: filing
A437: Indonesia | B437: Communication Services | C437: DNET.JK | D437: Indoritel | E437: Evidence | F437: community: community_investment | G437: FAST/KFC (associate) one-day community food-sharing event in Bandung | H437: Pada 16 Maret 2025, FAST menyelenggarakan kegiatan sosial bertajuk “Berbagi Berkah Bersama KFC” sebagai bentuk kepedulian kepada masyarakat sekitar. | I437: On March 16, 2025, FAST organized a community outreach event titled “Sharing Blessings with KFC” as a gesture of care for the local community. | J437: Annual report > Sustainability Report > CSR Activities in 2025 > FAST > Social | K437: filing
A438: Indonesia | B438: Communication Services | C438: DNET.JK | D438: Indoritel | E438: Evidence | F438: entrepreneurship: enabling | G438: Indomaret (associate) gives local MSMEs access to sell their products in its outlets | H438: Entitas asosiasi Perseroan, Indomaret, terus berupaya menyediakan lapangan kerja bagi warga sekitar dan akses bagi UMKM lokal untuk memasarkan produk-produknya di sebagian besar gerainya. | I438: The Company’s associate entity, Indomaret, continues to create employment opportunities for local communities and provide access for local MSMEs to market their products in many of its outlets. | J438: Annual report > Sustainability Report > Social Performance > Community [POJK A.6c3] | K438: filing
A439: Indonesia | B439: Communication Services | C439: DNET.JK | D439: Indoritel | E439: Evidence | F439: entrepreneurship: enabling | G439: Indomaret MoU with GP Ansor to support youth economic independence and empowerment | H439: Indomaret melakukan penandatanganan Nota Kesepahaman dengan Gerakan Pemuda (GP) Ansor yang bertujuan untuk mendukung kemandirian dan pemberdayaan ekonomi pemuda. | I439: Indomaret signed a Memorandum of Understanding with the Ansor Youth Movement (GP Ansor), which aims to support youth independence and economic empowerment. | J439: Annual report > Performance Highlights > 2025 Event Highlights > Indomaret | K439: filing
A440: Indonesia | B440: Communication Services | C440: DNET.JK | D440: Indoritel | E440: Evidence | F440: community: external_education | G440: Indomaret (associate) scholarships for children of the East Kalimantan Dayak Fellowship in Samarinda | H440: Pemberian beasiswa kepada putra-putri Persekutuan Dayak Kalimantan Timur (PDKT) di Lamin Bakuda Kota Samarinda. | I440: Provision of scholarships for students of the East Kalimantan Dayak Fellowship (PDKT) at Lamin Bakuda, Samarinda City. | J440: Annual report > Sustainability Report > CSR Activities in 2025 > Indomaret > Education | K440: filing
A441: Indonesia | B441: Communication Services | C441: DNET.JK | D441: Indoritel | E441: Evidence | F441: community: community_investment | G441: Indomaret (associate) Posyandu toddler health services and free health check-ups for the elderly | H441: Mengadakan Posyandu Balita & Cek Kesehatan yang mencakup acara senam sehat, penyuluhan kesehatan, pengecekan perkembangan balita, imunisasi, dan pengecekan kesehatan gratis bagi lansia. | I441: Organizing Integrated Health Service Post (Posyandu) activities for toddlers and health check-ups, including healthy exercise sessions, health education, toddler development monitoring, immunization, and free health check-ups for the elderly. | J441: Annual report > Sustainability Report > CSR Activities in 2025 > Indomaret > Health Programs | K441: filing
A442: Indonesia | B442: Communication Services | C442: DNET.JK | D442: Indoritel | E442: Evidence | F442: community: community_investment | G442: Indomaret (associate) mosquito-breeding eradication and dengue prevention education with local health offices | H442: Menyelenggarakan Pemberantasan Sarang Nyamuk (PSN) bersama Jumantik (Juru Pemantau Jentik) dan Dinas Kesehatan di kota masing-masing untuk memberikan penyuluhan terkait pencegahan demam berdarah. | I442: Organizing Mosquito Breeding Eradication (PSN) activities together with Jumantik (Larvae Monitoring Officers) and local Health Offices to provide education on dengue fever prevention. | J442: Annual report > Sustainability Report > CSR Activities in 2025 > Indomaret > Health Programs | K442: filing
A443: Indonesia | B443: Communication Services | C443: DNET.JK | D443: Indoritel | E443: Evidence | F443: community: community_investment | G443: FiberStar (subsidiary) disaster recovery support in Sukabumi: emergency telecom infrastructure and donations | H443: Akibat bencana banjir dan tanah longsor yang mengakibatkan kerusakan di beberapa kecamatan di Kabupaten Sukabumi, FiberStar berinisiatif membantu pemulihan bencana dengan menyediakan infrastruktur layanan internet dan telekomunikasi untuk memastikan komunikasi tetap berjalan, serta memberikan donasi untuk mendukung pemulihan yang lebih tangguh dan berkelanjutan setelah bencana. | I443: Following floods and landslides that caused damage in several districts in Sukabumi Regency, FiberStar took the initiative to support disaster recovery by providing internet and telecommunications service infrastructure to ensure communication continuity, as well as donating to support a stronger and more sustainable post-disaster recovery. | J443: Annual report > Sustainability Report > CSR Activities in 2025 > FiberStar | K443: filing
A444: Indonesia | B444: Communication Services | C444: DNET.JK | D444: Indoritel | E444: Evidence | F444: community: community_investment | G444: FiberStar (subsidiary) humanitarian aid and Starlink emergency internet for Sumatra flood victims | H444: Akibat adanya bencana banjir bandang dan tanah longsor besar yang melanda Sumatera, FiberStar berinisiatif membantu dengan menyalurkan bantuan logistik bagi masyarakat terdampak serta menyediakan akses internet darurat Starlink untuk memastikan komunikasi dan koordinasi tim di lapangan tetap berjalan lancar. | I444: Following severe flash floods and landslides that struck Sumatra, FiberStar provided logistical assistance to affected communities and deployed Starlink emergency internet access to ensure communication and coordination among field teams remained operational. | J444: Annual report > Sustainability Report > CSR Activities in 2025 > FiberStar | K444: filing
A445: Indonesia | B445: Communication Services | C445: DNET.JK | D445: Indoritel | E445: Evidence | F445: community: community_investment | G445: Indomaret (associate) donation of an ambulance to North Lampung Regency | H445: Pemberian bantuan mobil ambulans untuk pelayanan kesehatan masyarakat Kabupaten Lampung Utara. | I445: Provision of an ambulance to support public healthcare services in North Lampung Regency. | J445: Annual report > Sustainability Report > CSR Activities in 2025 > Indomaret > Health Programs | K445: filing
A446: Indonesia | B446: Communication Services | C446: DNET.JK | D446: Indoritel | E446: Evidence | F446: community: community_investment | G446: Indomaret (associate) donation of agricultural equipment to Muna Regency | H446: Pemberian bantuan alat pertanian untuk Kabupaten Muna. | I446: Provision of agricultural equipment assistance for Muna Regency. | J446: Annual report > Sustainability Report > CSR Activities in 2025 > Indomaret > Economic | K446: filing
... A500: Indonesia | B500: Consumer Staples | C500: HMSP.JK | D500: Sampoerna | E500: Internal finding (no deduction) | F500: rights_finding (found by: internal) | G500: The internal Ethics & Compliance process substantiated 36 cases in 2025. Case types are not broken out and may be mostly non-rights matters such as fraud. No finding by a court, regulator or outside body is disclosed, so this costs no points. | H500: Dari seluruh laporan, 36 laporan memiliki bukti yang cukup bagi Perseroan untuk memberi sanksi kepada karyawan bersangkutan. | I500: Of all reports, 36 had sufficient evidence for the Company to sanction the employees concerned. | J500: Annual report > Corporate Governance > Code of Conduct / Speak Up | K500: filing
A501: Indonesia | B501: Financials | C501: BMRI.JK | D501: Bank Mandiri | E501: Evidence | F501: creativity: enables | G501: Supports Indonesia's creative/craft industry through the INACRAFT craft exhibition | H501: Bank Mandiri Supports Creative Industry at INACRAFT as a Momentum for the 27th Anniversary: Synergy to Advance the Country | J501: Annual report > Corporate Governance > Press releases list | K501: filing
A502: Indonesia | B502: Financials | C502: BMRI.JK | D502: Bank Mandiri | E502: Evidence | F502: cross_cultural: internal_practice; community: external_education | G502: Kriya Mandiri internship, including a contact-center internship track for people with disabilities | H502: For the contact center position, the Bank also offers a specialized internship program for participants with disabilities, known as Kriya Mandiri Contact Center, designed for applicants with a minimum education level of high school. | J502: Annual report > Management Discussion and Analysis > Human Capital > Recruitment | K502: filing
A503: Indonesia | B503: Financials | C503: BMRI.JK | D503: Bank Mandiri | E503: Evidence | F503: cross_cultural: customer_access | G503: KUR loan product designed for Indonesian migrant workers | H503: KUR for Migrant Workers (KUR TKI), for loan ceilings up to Rp25 million per borrower, with a tenure aligned to the employment contract or a maximum of 12 months. | J503: Annual report > ESG Implementation Report > For Communities > People's Business Loan (KUR) | K503: filing
A504: Indonesia | B504: Financials | C504: BMRI.JK | D504: Bank Mandiri | E504: Evidence | F504: entrepreneurship: enabling | G504: Livin' Merchant: free point-of-sale and QRIS payment app for micro and small merchants | H504: To advance financial inclusion, Livin’ Merchant provides an affordable payment solution for MSMEs, with 3 million registered users, 63% of whom are located in non-urban areas. | J504: Annual report > Report of the Board of Directors | K504: filing
A505: Indonesia | B505: Financials | C505: BMRI.JK | D505: Bank Mandiri | E505: Evidence | F505: entrepreneurship: enabling | G505: Government-backed People's Business Credit (KUR) for businesses lacking sufficient collateral | H505: From the start of the program in 2008 up to 2025, the Bank has disbursed KUR to 963,340 million borrowers, with a total financing value of Rp68.5 trillion. | J505: Annual report > ESG Implementation Report > For Communities > People's Business Loan (KUR) | K505: filing
A506: Indonesia | B506: Financials | C506: BMRI.JK | D506: Bank Mandiri | E506: Evidence | F506: entrepreneurship: enabling; community: external_education | G506: Mandiri UKM Center providing MSMEs with credit access, literacy, mentoring and tax/financial advisory | H506: Mandiri UKMC Objectives: Providing a platform for MSMEs to access credit financing more quickly and easily while improving their competencies through literacy programs, mentoring, and training, such as tax advisory, financial report education, and more. | J506: Annual report > ESG Implementation Report > For Our Customers > Financial literacy programs | K506: filing
A507: Indonesia | B507: Financials | C507: BMRI.JK | D507: Bank Mandiri | E507: Evidence | F507: community: employee_development | G507: Employee education and training through Mandiri Corporate University | H507: Meanwhile, the realization of education and training expenses amounted to Rp326.4 billion as of December 2025, representing 70.9% of the 2025 competency development budget target. | J507: Annual report > Management Discussion and Analysis | K507: filing
A508: Indonesia | B508: Financials | C508: BMRI.JK | D508: Bank Mandiri | E508: Evidence | F508: community: community_investment | G508: Aksi Bersih Mandiri environmental volunteering with employees and local communities | H508: The initiative successfully collected and recycled approximately 12.7 tonnes of inorganic waste and involved more than 1,350 volunteers from Bank Mandiri employees and surrounding communities. | J508: Annual report > Social and Environmental Responsibility > Aksi Bersih Mandiri | K508: filing
A509: Indonesia | B509: Financials | C509: BMRI.JK | D509: Bank Mandiri | E509: Evidence | F509: creativity: enables | G509: Livin' Fest events across several cities showcasing MSMEs and the creative economy | H509: Celebrating the 27th Anniversary, Bank Mandiri Holds Livin' Fest with Synergy of MSMEs and Creative Economy | J509: Annual report > Corporate Governance > Press releases list | K509: filing
A510: Indonesia | B510: Financials | C510: BMRI.JK | D510: Bank Mandiri | E510: Evidence | F510: community: external_education; entrepreneurship: enabling | G510: Rumah BUMN centres providing training, capacity building and digitalisation for MSMEs | H510: As of 2025, a total of 17.6 thousand MSMEs had participated in the program, with 7,928 MSMEs successfully moving up a level, supported by more than 295 training programs. | J510: Annual report > Social and Environmental Responsibility > Rumah BUMN (RB) | K510: filing
A511: Indonesia | B511: Financials | C511: BMRI.JK | D511: Bank Mandiri | E511: Evidence | F511: community: community_investment | G511: Mandiri Peduli Sekolah school refurbishment and reading corners with employee volunteers | H511: In 2025, the program was implemented in 27 schools across Indonesia, involving employees and community members as volunteers to strengthen social engagement and community care. | J511: Annual report > Social and Environmental Responsibility > Mandiri Peduli Sekolah | K511: filing
A512: Indonesia | B512: Financials | C512: BMRI.JK | D512: Bank Mandiri | E512: Evidence | F512: community: community_investment | G512: Annual social and environmental responsibility (TJSL) spending on community development | H512: As such. the Bank integrates social and environmental considerations into its strategy and operations and has allocated Rp251.1 billion in 2025 to support community development and environmental initiatives. | J512: Annual report > Corporate Governance > Funding to Social and/or Political Activities | K512: filing
... A516: Indonesia | B516: Financials | C516: BMRI.JK | D516: Bank Mandiri | E516: Evidence | F516: cross_cultural: customer_access | G516: Tailored savings accounts for persons with disabilities, including those without a national ID number | H516: Bank Mandiri also strengthens financial inclusion for persons with disabilities through the Inclusive Economic Acceleration Program, which includes opening 10,000 new savings accounts across West Java, Central Java, and Yogyakarta. | J516: Annual report > ESG Implementation Report > For Communities > Mandiri Makmur Savings (SiMakmur) | K516: filing
A517: Indonesia | B517: Financials | C517: BBNI.JK | D517: Bank Negara Indonesia | E517: Evidence | F517: creativity: enables | G517: Title sponsorship of the BNI Java Jazz Festival 2025 music festival, run alongside customer promotions | H517: Sebagai bagian dukungan BNI dalam event International BNI Java Jazz Festival 2025, BNI menyiapkan deretan promo menarik selama festival musik terbesar di Asia Tenggara tersebut berlangsung. | I517: As part of BNI's support for the International BNI Java Jazz Festival 2025, BNI prepared a series of attractive promotions during the largest music festival in Southeast Asia. | J517: Annual report > Peristiwa Penting 2025 > 30 Mei - 1 Juni BNI Java Jazz Festival 2025 | K517: filing
A518: Indonesia | B518: Financials | C518: BBNI.JK | D518: Bank Negara Indonesia | E518: Evidence | F518: community: community_investment | G518: Grants to places of worship of various religions | H518: Pada tahun 2025, BNI telah menyalurkan bantuan kepada 142 sarana ibadah dari berbagai agama yang tersebar di berbagai wilayah kerja BNI. | I518: In 2025, BNI provided assistance to 142 places of worship of various religions across BNI's working areas. | J518: Annual report > Tanggung Jawab Sosial dan Lingkungan > Dukungan untuk Kota dan Pemukiman > Sarana Ibadah | K518: filing
A519: Indonesia | B519: Financials | C519: BBNI.JK | D519: Bank Negara Indonesia | E519: Evidence | F519: cross_cultural: customer_access | G519: BNI Agen46 branchless-banking agent network extending financial services to remote and underserved (3T) regions | H519: Dalam rangka memperluas jangkauan, BNI memiliki 217 .013 Agen46 dengan 28.177 Agen atau sekitar 13% berada di wilayah 3T BNI Agen46 yang merupakan mitra BNI dalam menyediakan layanan perbankan kepada masyarakat dalam rangka keuangan inklusif. | I519: To expand reach, BNI has 217,013 Agen46 agents, of which 28,177 (about 13%) are in frontier, outermost and disadvantaged (3T) regions; Agen46 are BNI partners providing banking services to the public for financial inclusion. | J519: Annual report > Komitmen ESG > Inklusi Keuangan > BNI Agen46 | K519: filing
A520: Indonesia | B520: Financials | C520: BBNI.JK | D520: Bank Negara Indonesia | E520: Evidence | F520: cross_cultural: customer_access; entrepreneurship: enabling | G520: Support for 10 small businesses run by people with disabilities, with the Ministry of Social Affairs | H520: BNI juga berkolaborasi dengan Kementerian Sosial Republik Indonesia dalam memberikan dukungan kepada 10 UMKM disabilitas, berupa bantuan peralatan usaha, pendampingan pengembangan usaha, pendampingan pengelolaan media sosial, serta penyediaan alat bantu disabilitas. | I520: BNI also worked with the Ministry of Social Affairs to support 10 MSMEs run by people with disabilities, with business equipment, business development mentoring, social media coaching and assistive devices. | J520: Annual report > Tanggung Jawab Sosial dan Lingkungan > Pilar Ekonomi > Pemberdayaan Penyandang Disabilitas | K520: filing
A521: Indonesia | B521: Financials | C521: BBNI.JK | D521: Bank Negara Indonesia | E521: Evidence | F521: cross_cultural: customer_access | G521: Capacity building and financial literacy for Indonesian migrant workers (PMI) in Hong Kong via BNI Remittance | H521: BNI Remittance juga aktif terlibat dalam beberapa kegiatan dengan PMI seperti capacity building , literasi keuangan, kunjungan ke komunitas-komunitas PMI di Hong Kong, dan lain sebagainya. | I521: BNI Remittance is also actively involved in activities with Indonesian migrant workers (PMI), such as capacity building, financial literacy and visits to PMI communities in Hong Kong. | J521: Annual report > Analisis dan Pembahasan > Perusahaan Anak > BNI Remittance | K521: filing
A522: Indonesia | B522: Financials | C522: BBNI.JK | D522: Bank Negara Indonesia | E522: Evidence | F522: entrepreneurship: enabling | G522: BNI Xpora program helping MSMEs export (financing, business matching, training modules, legal setup) | H522: Hingga 31 Desember 2025, program BNI Xpora telah mendorong 12.094 pelaku UMKM untuk meraih pasar global. | I522: As of 31 December 2025, the BNI Xpora program has helped 12,094 MSMEs reach global markets. | J522: Annual report > Fungsi Penunjang Bisnis > Teknologi Informasi > BNI Xpora | K522: filing
A523: Indonesia | B523: Financials | C523: BBNI.JK | D523: Bank Negara Indonesia | E523: Evidence | F523: entrepreneurship: enabling | G523: Launch of hi by hibank app for MSME business management, financing and development | H523: Pada tahun 2025, hibank secara resmi meluncurkan aplikasi mobile banking hi by hibank sebagai solusi digital terintegrasi yang dirancang khusus untuk mendukung digitalisasi serta pengembangan UMKM di Indonesia. | I523: In 2025, hibank officially launched the hi by hibank mobile banking app as an integrated digital solution designed specifically to support the digitalization and development of MSMEs in Indonesia. | J523: Annual report > Profil Perusahaan > Perusahaan Anak > PT Bank Hibank Indonesia | K523: filing
A524: Indonesia | B524: Financials | C524: BBNI.JK | D524: Bank Negara Indonesia | E524: Evidence | F524: entrepreneurship: enabling | G524: BNIdirect bisnis digital banking platform designed for MSMEs | H524: Salah satu inovasi utama yang diluncurkan pada Agustus 2025 adalah BNIdirect bisnis, sebuah platform digital yang dirancang khusus untuk merangkul dan mempermudah bisnis berskala UMKM agar dapat menikmati layanan perbankan digital yang setara dengan perusahaan korporasi. | I524: A key innovation launched in August 2025 is BNIdirect bisnis, a digital platform designed specifically to bring MSME-scale businesses digital banking services on par with corporations. | J524: Annual report > Analisis dan Pembahasan > Corporate Banking > Keunggulan Kompetitif dan Inovasi | K524: filing
A525: Indonesia | B525: Financials | C525: BBNI.JK | D525: Bank Negara Indonesia | E525: Evidence | F525: entrepreneurship: enabling | G525: BNI Ventures BNV Arcade startup acceleration and incubation program | H525: Dalam rangkaian aktivitas tersebut, BNI Ventures menyelenggarakan program akselerasi dan inkubasi dengan menggandeng mitra strategis, serta membuka pintu match-making antara perusahaan rintisan dengan unit bisnis terkait di BNI Group. | I525: In these activities, BNI Ventures runs acceleration and incubation programs with strategic partners and opens match-making between startups and relevant BNI Group business units. | J525: Annual report > Analisis dan Pembahasan > Perusahaan Anak > BNI Ventures | K525: filing
A526: Indonesia | B526: Financials | C526: BBNI.JK | D526: Bank Negara Indonesia | E526: Evidence | F526: entrepreneurship: enabling | G526: Government-subsidized People's Business Credit (KUR) for micro, small and medium businesses | H526: Kredit Usaha Rakyat (KUR) merupakan program pembiayaan bersubsidi dari pemerintah yang dirancang untuk meningkatkan akses permodalan bagi Usaha Mikro, Kecil, dan Menengah (UMKM). | I526: People's Business Credit (KUR) is a government-subsidized financing program designed to improve access to capital for micro, small and medium enterprises. | J526: Annual report > Analisis dan Pembahasan > SME Business & Business Program | K526: filing
A527: Indonesia | B527: Financials | C527: BBNI.JK | D527: Bank Negara Indonesia | E527: Evidence | F527: creativity: enables | G527: Support for the Indonesian film industry through a collaboration on the film TIMUR (press-release headline only) | H527: BNI Dukung Industri Film Nasional Lewat Kolaborasi dengan Iko Uwais di Film TIMUR | I527: BNI supports the national film industry through a collaboration with Iko Uwais on the film TIMUR | J527: Annual report > Tata Kelola Perusahaan > Akses Informasi > Siaran Pers 2025 | K527: filing
A528: Indonesia | B528: Financials | C528: BBNI.JK | D528: Bank Negara Indonesia | E528: Evidence | F528: community: external_education | G528: Character-education program for schools and international English certification for teachers in West Nusa Tenggara | H528: Program ini menjangkau 10 sekolah di Lombok dengan melibatkan 3.400 siswa, 150 guru, dan 390 orang tua melalui penguatan pendidikan karakter yang menekankan sinergi antara sekolah dan keluarga. | I528: The program reached 10 schools in Lombok, involving 3,400 students, 150 teachers and 390 parents, by strengthening character education that emphasizes synergy between school and family. | J528: Annual report > Tanggung Jawab Sosial dan Lingkungan > Pelaksanaan Program TJSL > Pendidikan | K528: filing
... A534: Indonesia | B534: Financials | C534: BBNI.JK | D534: Bank Negara Indonesia | E534: Evidence | F534: community: employee_development | G534: Company-wide employee training through BNI Corporate University | H534: Sepanjang tahun 2025, BNI telah menyelenggarakan berbagai program pendidikan dan pelatihan yang diikuti oleh 26.937 pegawai atau setara dengan 99,96% dari total pegawai BNI. | I534: During 2025, BNI ran various education and training programs attended by 26,937 employees, or 99.96% of all BNI employees. | J534: Annual report > Komitmen ESG > Pengembangan Sumber Daya Manusia > Praktik | K534: filing
A535: Singapore | B535: Financials | C535: O39.SI | D535: OCBC Bank | E535: Evidence | F535: community: external_education | G535: OCBC SeniorCare programme supporting seniors' health, wealth, literacy and lifestyle needs | H535: With over $2 million invested to support more than 180,000 seniors, the programme helps seniors manage their health, wealth, literacy and lifestyle needs with confidence. | J535: Annual report > Group CEO statement > Investing in People, Communities and Sustainability | K535: filing
A536: Singapore | B536: Financials | C536: O39.SI | D536: OCBC Bank | E536: Evidence | F536: community: employee_development | G536: Coaching for Growth programme with ICF-trained internal coaches | H536: As of December 2025, our community of 52 ICF-trained coaches has inspired and guided more than 300 employees, empowering them to grow with confidence and unlock their fullest personal and professional potential. | J536: Annual report > Our People > Coaching | K536: filing
A537: Singapore | B537: Financials | C537: O39.SI | D537: OCBC Bank | E537: Evidence | F537: community: employee_development | G537: AI, Digital and Data training for employees | H537: In the past three years, around three in five employees have participated in training programmes related to AI, Digital and Data. | J537: Annual report > Tech Shift > Workforce capabilities | K537: filing
A538: Singapore | B538: Financials | C538: O39.SI | D538: OCBC Bank | E538: Evidence | F538: community: employee_development | G538: Cyber Certification Pathway 2.0 upskilling employees into cybersecurity roles | H538: Over 200 graduates from key markets including Singapore, Malaysia, Mainland China and Hong Kong have completed the programme | J538: Annual report > 2025 Sustainability Highlights > Conducting Our Business Responsibly | K538: filing
A539: Singapore | B539: Financials | C539: O39.SI | D539: OCBC Bank | E539: Evidence | F539: creativity: enables | G539: 'Life in a Snapshot' photography and storytelling programme for seniors with dementia, ending in a public artwork showcase | H539: OCBC volunteers delved into in-depth conversations with the seniors and continued to engage them over six months to hold a public showcase featuring artwork reflecting stories from their lives. | J539: Annual report > Helping Where it Matters > Hong Kong > Life in a Snapshot | K539: filing
A540: Singapore | B540: Financials | C540: O39.SI | D540: OCBC Bank | E540: Evidence | F540: entrepreneurship: enabling | G540: Women Unlimited programme supporting women entrepreneurs across four markets | H540: Our Women Unlimited programme now extends across Singapore, Indonesia, Hong Kong and Malaysia, with a goal to support 10,000 women entrepreneurs by 2030. | J540: Annual report > Group CEO statement > SME programmes | K540: filing
A541: Singapore | B541: Financials | C541: O39.SI | D541: OCBC Bank | E541: Evidence | F541: entrepreneurship: enabling | G541: Serial Entrepreneur programme supporting founders of multiple small businesses | H541: The Serial Entrepreneur programme, which supports founders who own multiple small businesses, was also expanded in 2025 across our core markets. | J541: Annual report > Group CEO statement > SME programmes | K541: filing
A542: Singapore | B542: Financials | C542: O39.SI | D542: OCBC Bank | E542: Evidence | F542: entrepreneurship: enabling | G542: OCBC SME Start-ESG Programme giving SMEs grant-funded assessment, expert advice and loan access | H542: The Programme helps SMEs obtain a baseline measurement of their sustainability metrics with a grant from EnterpriseSG, expert advice on sustainability practices and access to sustainability-linked loans (SLLs) from OCBC. | J542: Annual report > Global Commercial Banking > Supporting SMEs | K542: filing
A543: Singapore | B543: Financials | C543: O39.SI | D543: OCBC Bank | E543: Evidence | F543: entrepreneurship: enabling | G543: Singpass authentication to ease cross-border business account opening | H543: To reduce friction for cross-border business formation, we became the first bank to enable Singpass authentication for Singaporeans opening business accounts in Malaysia. | J543: Annual report > Global Commercial Banking > Johor | K543: filing
A544: Singapore | B544: Financials | C544: O39.SI | D544: OCBC Bank | E544: Evidence | F544: cross_cultural: customer_access | G544: Dialect-speaking branch ambassadors for seniors and accessible app text resizing | H544: We introduced OCBC CARE Ambassadors in selected branches to assist seniors in familiar dialects and enhanced digital accessibility with smart text resizing on the OCBC mobile app. | J544: Annual report > Group CEO statement > Investing in People, Communities and Sustainability | K544: filing
A545: Singapore | B545: Financials | C545: O39.SI | D545: OCBC Bank | E545: Evidence | F545: cross_cultural: customer_access | G545: Pay-to-wallet remittance feature aimed at the unbanked and Singapore's foreign workforce | H545: Expanded the OCBC app’s pay-to-wallet feature to cover 10 leading digital wallets across Asia, improving remittance speed, cost and accessibility especially for the region’s unbanked population and Singapore’s foreign workforce | J545: Annual report > 2025 Sustainability Highlights > Bringing Impact to Communities | K545: filing
A546: Singapore | B546: Financials | C546: O39.SI | D546: OCBC Bank | E546: Evidence | F546: cross_cultural: connecting_communities; community: community_investment | G546: OCBC-SDSC SwimTogether water safety programme for persons with disabilities, fully funded by OCBC | H546: Fully funded by OCBC, the programme supports 100 participants across 800 classes led by trained coaches and OCBC staff volunteers. | J546: Annual report > Helping Where it Matters > Singapore > OCBC-SDSC SwimTogether Programme | K546: filing
... A660: Singapore | B660: Real Estate | C660: A17U.SI | D660: CapitaLand Ascendas REIT | E660: Evidence | F660: cross_cultural: demographics_only | G660: Board diversity policy with gender targets for female directors | H660: To have at least 25% and 30% female Directors on the Board during the period leading up to 2025 and 2030. | J660: Annual report > Corporate Governance > Board Diversity > Diversity Targets, Plans and Timelines | K660: filing

Sheet Dropped
A1: Country | B1: Sector | C1: Ticker | D1: Company | E1: Why it was dropped
A2: Switzerland | B2: Materials | C2: EMSN.SW | D2: Ems-Chemie | E2: dropped by the team (Oct 23): annual report has too little narrative text to score (1,629 words, under 2,000)
A3: Indonesia | B3: Communication Services | C3: ISAT.JK | D3: Indosat | E3: dropped by the team (Oct 23): annual report download blocked (IDX and company site)
A4: Indonesia | B4: Consumer Staples | C4: UNVR.JK | D4: Unilever Indonesia | E4: dropped by the team (Oct 23): annual report download blocked (IDX and company site)
A5: Indonesia | B5: Consumer Staples | C5: ICBP.JK | D5: Indofood CBP | E5: dropped by the team (Oct 23): annual report download blocked (IDX and company site)
A6: Indonesia | B6: Financials | C6: BDMN.JK | D6: Bank Danamon | E6: dropped by the team (Oct 23): annual report download blocked (IDX and company site)
A7: Indonesia | B7: Financials | C7: BBRI.JK | D7: Bank Rakyat Indonesia | E7: dropped by the team (Oct 23): annual report download blocked (IDX and company site)
A8: Singapore | B8: Financials | C8: SWICH.AS | D8: SWI Capital Holding | E8: identity unclear: check ticker/name with the team.
